Workbook
Name Slicer_Brocker: #N/A
Name Slicer_Broker: #N/A
Name Slicer_Camion: #N/A
Name Slicer_Clientes: #N/A
Name Slicer_Factura1: #N/A
Name Slicer_Fecha1: #N/A
Name Slicer_Proveedor: #N/A
Name Slicer_Proyecto: #N/A
Name Slicer_Proyecto1: #N/A

Sheet Facturas Generales
A1: Fecha | B1: Key_Fact | C1: Factura | D1: Truck | E1: Broker | F1: Observaciones | G1: Camion | H1: Ticket | I1: Clientes | J1: Proyecto | K1: Proyecto OK | L1: Job Ok | M1: Volcadero | N1: TicketVolcadero | O1: Material | P1: Horas o Viaje | Q1: Costo unitario | R1: Total Cobrado | S1: Pago a Broker | T1: Unamed
A2: 13-1-2025 | B2: =tbl_Facturas[[#This Row],[Factura]] & "|" & tbl_Facturas[[#This Row],[Proyecto OK]] & "|" & TEXT(tbl_Facturas[[#This Row],[Horas o Viaje]],"0.00") & "|" & TEXT(tbl_Facturas[[#This Row],[Costo unitario]],"0.00") -> 2328|Lead Service Replacement Project|8.00|115.50 | C2: 2328 | D2: 11 | E2: MLB | G2: 11 | H2: 10818 | I2: Millenium | J2: Lead Service Replacement Project | K2: Lead Service Replacement Project | P2: 8 | Q2: 115.5 | R2: 924 | S2: =IFERROR(_xlfn.XLOOKUP(tbl_Facturas[[#This Row],[Key_Fact]],tbl_Manifiestos[Key_Manif],tbl_Manifiestos[Pagado a Broker],0),0) -> 859.32 | T2: 19.95
A3: 13-1-2025 | B3: =tbl_Facturas[[#This Row],[Factura]] & "|" & tbl_Facturas[[#This Row],[Proyecto OK]] & "|" & TEXT(tbl_Facturas[[#This Row],[Horas o Viaje]],"0.00") & "|" & TEXT(tbl_Facturas[[#This Row],[Costo unitario]],"0.00") -> 2328|Lead Service Replacement Project|8.00|115.50 | C3: 2328 | D3: 308 | E3: AAA | G3: 308 | H3: 11175 | I3: Millenium | J3: Lead Service Replacement Project | K3: Lead Service Replacement Project | P3: 8 | Q3: 115.5 | R3: 924 | S3: =IFERROR(_xlfn.XLOOKUP(tbl_Facturas[[#This Row],[Key_Fact]],tbl_Manifiestos[Key_Manif],tbl_Manifiestos[Pagado a Broker],0),0) -> 859.32 | T3: 943.95
A4: 13-1-2025 | B4: =tbl_Facturas[[#This Row],[Factura]] & "|" & tbl_Facturas[[#This Row],[Proyecto OK]] & "|" & TEXT(tbl_Facturas[[#This Row],[Horas o Viaje]],"0.00") & "|" & TEXT(tbl_Facturas[[#This Row],[Costo unitario]],"0.00") -> 2329|Niles IL|11.00|115.50 | C4: 2329 | D4: 73 | E4: LI | G4: 73 | H4: 11994 | I4: Millenium | J4: Niles IL | K4: Niles IL | M4: Reliable Pulaski | P4: 11 | Q4: 115.5 | R4: 1270.5 | S4: =IFERROR(_xlfn.XLOOKUP(tbl_Facturas[[#This Row],[Key_Fact]],tbl_Manifiestos[Key_Manif],tbl_Manifiestos[Pagado a Broker],0),0) -> 0 | T4: 2214.45
A5: 13-1-2025 | B5: =tbl_Facturas[[#This Row],[Factura]] & "|" & tbl_Facturas[[#This Row],[Proyecto OK]] & "|" & TEXT(tbl_Facturas[[#This Row],[Horas o Viaje]],"0.00") & "|" & TEXT(tbl_Facturas[[#This Row],[Costo unitario]],"0.00") -> 2329|Niles IL|7.00|115.50 | C5: 2329 | D5: 19 | E5: MLB | G5: 19 | H5: 11689 | I5: Millenium | J5: Niles IL | K5: Niles IL | M5: Reliable Lyons | P5: 7 | Q5: 115.5 | R5: 808.5 | S5: =IFERROR(_xlfn.XLOOKUP(tbl_Facturas[[#This Row],[Key_Fact]],tbl_Manifiestos[Key_Manif],tbl_Manifiestos[Pagado a Broker],0),0) -> 751.905 | T5: 3022.95
A6: 13-1-2025 | B6: =tbl_Facturas[[#This Row],[Factura]] & "|" & tbl_Facturas[[#This Row],[Proyecto OK]] & "|" & TEXT(tbl_Facturas[[#This Row],[Horas o Viaje]],"0.00") & "|" & TEXT(tbl_Facturas[[#This Row],[Costo unitario]],"0.00") -> 2330|Lead Replacement Service|9.00|110.00 | C6: 2330 | D6: 67 | E6: LT | G6: 67 | H6: 11612 | I6: PanOceanic | J6: 3347 | K6: Lead Replacement Service | L6: 3347 | P6: 9 | Q6: 110 | R6: 990 | S6: =IFERROR(_xlfn.XLOOKUP(tbl_Facturas[[#This Row],[Key_Fact]],tbl_Manifiestos[Key_Manif],tbl_Manifiestos[Pagado a Broker],0),0) -> 920.7 | T6: 4012.95
A7: 13-1-2025 | B7: =tbl_Facturas[[#This Row],[Factura]] & "|" & tbl_Facturas[[#This Row],[Proyecto OK]] & "|" & TEXT(tbl_Facturas[[#This Row],[Horas o Viaje]],"0.00") & "|" & TEXT(tbl_Facturas[[#This Row],[Costo unitario]],"0.00") -> 2330|Lead Replacement Service|9.00|110.00 | C7: 2330 | D7: 198 | E7: POSADA | G7: 198 | H7: 11426 | I7: PanOceanic | J7: 3347 | K7: Lead Replacement Service | L7: 3347 | P7: 9 | Q7: 110 | R7: 990 | S7: =IFERROR(_xlfn.XLOOKUP(tbl_Facturas[[#This Row],[Key_Fact]],tbl_Manifiestos[Key_Manif],tbl_Manifiestos[Pagado a Broker],0),0) -> 920.7 | T7: 5002.95
A8: 13-1-2025 | B8: =tbl_Facturas[[#This Row],[Factura]] & "|" & tbl_Facturas[[#This Row],[Proyecto OK]] & "|" & TEXT(tbl_Facturas[[#This Row],[Horas o Viaje]],"0.00") & "|" & TEXT(tbl_Facturas[[#This Row],[Costo unitario]],"0.00") -> 2330|Lead Replacement Service|8.50|110.00 | C8: 2330 | D8: 19 | E8: MLB | G8: 19 | H8: 11688 | I8: PanOceanic | J8: 3347 | K8: Lead Replacement Service | L8: 3347 | P8: 8.5 | Q8: 110 | R8: 935 | S8: =IFERROR(_xlfn.XLOOKUP(tbl_Facturas[[#This Row],[Key_Fact]],tbl_Manifiestos[Key_Manif],tbl_Manifiestos[Pagado a Broker],0),0) -> 869.55 | T8: 5937.95
A9: 13-1-2025 | B9: =tbl_Facturas[[#This Row],[Factura]] & "|" & tbl_Facturas[[#This Row],[Proyecto OK]] & "|" & TEXT(tbl_Facturas[[#This Row],[Horas o Viaje]],"0.00") & "|" & TEXT(tbl_Facturas[[#This Row],[Costo unitario]],"0.00") -> 2330|Lead Replacement Service|9.50|110.00 | C9: 2330 | D9: 325 | E9: LT | G9: 325 | H9: 10563 | I9: PanOceanic | J9: 3347 | K9: Lead Replacement Service | L9: 3347 | P9: 9.5 | Q9: 110 | R9: 1045 | S9: =IFERROR(_xlfn.XLOOKUP(tbl_Facturas[[#This Row],[Key_Fact]],tbl_Manifiestos[Key_Manif],tbl_Manifiestos[Pagado a Broker],0),0) -> 971.85 | T9: 6982.95
A10: 13-1-2025 | B10: =tbl_Facturas[[#This Row],[Factura]] & "|" & tbl_Facturas[[#This Row],[Proyecto OK]] & "|" & TEXT(tbl_Facturas[[#This Row],[Horas o Viaje]],"0.00") & "|" & TEXT(tbl_Facturas[[#This Row],[Costo unitario]],"0.00") -> 2330|Lead Replacement Service|10.50|110.00 | C10: 2330 | D10: 617 | E10: LT | G10: 617 | H10: 10564 | I10: PanOceanic | J10: 3347 | K10: Lead Replacement Service | L10: 3347 | P10: 10.5 | Q10: 110 | R10: 1155 | S10: =IFERROR(_xlfn.XLOOKUP(tbl_Facturas[[#This Row],[Key_Fact]],tbl_Manifiestos[Key_Manif],tbl_Manifiestos[Pagado a Broker],0),0) -> 1074.15 | T10: 8137.95
A11: 20-1-2025 | B11: =tbl_Facturas[[#This Row],[Factura]] & "|" & tbl_Facturas[[#This Row],[Proyecto OK]] & "|" & TEXT(tbl_Facturas[[#This Row],[Horas o Viaje]],"0.00") & "|" & TEXT(tbl_Facturas[[#This Row],[Costo unitario]],"0.00") -> 2331|Canal #2 |1.00|199.50 | C11: 2331 | D11: 67 | F11: LT | G11: 67 | H11: 11614 | I11: FHP | J11: Canal #2Job# 6227 | K11: Canal #2 | L11: 6227 | M11: Vulcan Pershing | P11: 1 | Q11: 199.5 | R11: 199.5 | S11: =IFERROR(_xlfn.XLOOKUP(tbl_Facturas[[#This Row],[Key_Fact]],tbl_Manifiestos[Key_Manif],tbl_Manifiestos[Pagado a Broker],0),0) -> 0 | T11: 8337.45
A12: 20-1-2025 | B12: =tbl_Facturas[[#This Row],[Factura]] & "|" & tbl_Facturas[[#This Row],[Proyecto OK]] & "|" & TEXT(tbl_Facturas[[#This Row],[Horas o Viaje]],"0.00") & "|" & TEXT(tbl_Facturas[[#This Row],[Costo unitario]],"0.00") -> 2331|Canal #2 |1.50|132.30 | C12: 2331 | D12: 67 | F12: LT | G12: 67 | H12: 11615 | I12: FHP | J12: Canal #2Job# 6227 | K12: Canal #2 | L12: 6227 | M12: Vulcan Pershing | O12: WAITING TIME | P12: 1.5 | Q12: 132.3 | R12: 198.45 | S12: =IFERROR(_xlfn.XLOOKUP(tbl_Facturas[[#This Row],[Key_Fact]],tbl_Manifiestos[Key_Manif],tbl_Manifiestos[Pagado a Broker],0),0) -> 0 | T12: 8535.9
A13: 20-1-2025 | B13: =tbl_Facturas[[#This Row],[Factura]] & "|" & tbl_Facturas[[#This Row],[Proyecto OK]] & "|" & TEXT(tbl_Facturas[[#This Row],[Horas o Viaje]],"0.00") & "|" & TEXT(tbl_Facturas[[#This Row],[Costo unitario]],"0.00") -> 2331|Canal #2 |1.00|199.50 | C13: 2331 | D13: 67 | F13: LT | G13: 67 | H13: 11616 | I13: FHP | J13: Canal #2Job# 6227 | K13: Canal #2 | L13: 6227 | M13: Vulcan Pershing | P13: 1 | Q13: 199.5 | R13: 199.5 | S13: =IFERROR(_xlfn.XLOOKUP(tbl_Facturas[[#This Row],[Key_Fact]],tbl_Manifiestos[Key_Manif],tbl_Manifiestos[Pagado a Broker],0),0) -> 0 | T13: 8735.4
A14: 20-1-2025 | B14: =tbl_Facturas[[#This Row],[Factura]] & "|" & tbl_Facturas[[#This Row],[Proyecto OK]] & "|" & TEXT(tbl_Facturas[[#This Row],[Horas o Viaje]],"0.00") & "|" & TEXT(tbl_Facturas[[#This Row],[Costo unitario]],"0.00") -> 2331|Canal #2 |1.00|199.50 | C14: 2331 | D14: 67 | F14: LT | G14: 67 | H14: 11617 | I14: FHP | J14: Canal #2Job# 6227 | K14: Canal #2 | L14: 6227 | M14: Vulcan Pershing | P14: 1 | Q14: 199.5 | R14: 199.5 | S14: =IFERROR(_xlfn.XLOOKUP(tbl_Facturas[[#This Row],[Key_Fact]],tbl_Manifiestos[Key_Manif],tbl_Manifiestos[Pagado a Broker],0),0) -> 0 | T14: 8934.9
A15: 20-1-2025 | B15: =tbl_Facturas[[#This Row],[Factura]] & "|" & tbl_Facturas[[#This Row],[Proyecto OK]] & "|" & TEXT(tbl_Facturas[[#This Row],[Horas o Viaje]],"0.00") & "|" & TEXT(tbl_Facturas[[#This Row],[Costo unitario]],"0.00") -> 2331|Canal #2 |1.00|199.50 | C15: 2331 | D15: 67 | F15: LT | G15: 67 | H15: 11618 | I15: FHP | J15: Canal #2Job# 6227 | K15: Canal #2 | L15: 6227 | M15: Vulcan Pershing | P15: 1 | Q15: 199.5 | R15: 199.5 | S15: =IFERROR(_xlfn.XLOOKUP(tbl_Facturas[[#This Row],[Key_Fact]],tbl_Manifiestos[Key_Manif],tbl_Manifiestos[Pagado a Broker],0),0) -> 0 | T15: 9134.4
A16: 20-1-2025 | B16: =tbl_Facturas[[#This Row],[Factura]] & "|" & tbl_Facturas[[#This Row],[Proyecto OK]] & "|" & TEXT(tbl_Facturas[[#This Row],[Horas o Viaje]],"0.00") & "|" & TEXT(tbl_Facturas[[#This Row],[Costo unitario]],"0.00") -> 2331|Canal #2 |1.00|199.50 | C16: 2331 | D16: 67 | F16: LT | G16: 67 | H16: 11622 | I16: FHP | J16: Canal #2Job# 6227 | K16: Canal #2 | L16: 6227 | M16: Vulcan Pershing | P16: 1 | Q16: 199.5 | R16: 199.5 | S16: =IFERROR(_xlfn.XLOOKUP(tbl_Facturas[[#This Row],[Key_Fact]],tbl_Manifiestos[Key_Manif],tbl_Manifiestos[Pagado a Broker],0),0) -> 0 | T16: 9333.9
A17: 20-1-2025 | B17: =tbl_Facturas[[#This Row],[Factura]] & "|" & tbl_Facturas[[#This Row],[Proyecto OK]] & "|" & TEXT(tbl_Facturas[[#This Row],[Horas o Viaje]],"0.00") & "|" & TEXT(tbl_Facturas[[#This Row],[Costo unitario]],"0.00") -> 2331|Canal #2 |1.00|199.50 | C17: 2331 | D17: 19 | F17: MLB | G17: 19 | H17: 11682 | I17: FHP | J17: Canal #2Job# 6227 | K17: Canal #2 | L17: 6227 | M17: Vulcan Pershing | P17: 1 | Q17: 199.5 | R17: 199.5 | S17: =IFERROR(_xlfn.XLOOKUP(tbl_Facturas[[#This Row],[Key_Fact]],tbl_Manifiestos[Key_Manif],tbl_Manifiestos[Pagado a Broker],0),0) -> 0 | T17: 9533.4
A18: 20-1-2025 | B18: =tbl_Facturas[[#This Row],[Factura]] & "|" & tbl_Facturas[[#This Row],[Proyecto OK]] & "|" & TEXT(tbl_Facturas[[#This Row],[Horas o Viaje]],"0.00") & "|" & TEXT(tbl_Facturas[[#This Row],[Costo unitario]],"0.00") -> 2331|Canal #2 |1.00|199.50 | C18: 2331 | D18: 19 | F18: MLB | G18: 19 | H18: 11683 | I18: FHP | J18: Canal #2Job# 6227 | K18: Canal #2 | L18: 6227 | M18: Vulcan Pershing | P18: 1 | Q18: 199.5 | R18: 199.5 | S18: =IFERROR(_xlfn.XLOOKUP(tbl_Facturas[[#This Row],[Key_Fact]],tbl_Manifiestos[Key_Manif],tbl_Manifiestos[Pagado a Broker],0),0) -> 0 | T18: 9732.9
A19: 20-1-2025 | B19: =tbl_Facturas[[#This Row],[Factura]] & "|" & tbl_Facturas[[#This Row],[Proyecto OK]] & "|" & TEXT(tbl_Facturas[[#This Row],[Horas o Viaje]],"0.00") & "|" & TEXT(tbl_Facturas[[#This Row],[Costo unitario]],"0.00") -> 2331|Canal #2 |1.75|132.30 | C19: 2331 | D19: 19 | F19: MLB | G19: 19 | H19: 11684 | I19: FHP | J19: Canal #2Job# 6227 | K19: Canal #2 | L19: 6227 | M19: Vulcan Pershing | O19: WAITING TIME | P19: 1.75 | Q19: 132.3 | R19: 231.53 | S19: =IFERROR(_xlfn.XLOOKUP(tbl_Facturas[[#This Row],[Key_Fact]],tbl_Manifiestos[Key_Manif],tbl_Manifiestos[Pagado a Broker],0),0) -> 0 | T19: 9964.43
A20: 20-1-2025 | B20: =tbl_Facturas[[#This Row],[Factura]] & "|" & tbl_Facturas[[#This Row],[Proyecto OK]] & "|" & TEXT(tbl_Facturas[[#This Row],[Horas o Viaje]],"0.00") & "|" & TEXT(tbl_Facturas[[#This Row],[Costo unitario]],"0.00") -> 2331|Canal #2 |1.00|199.50 | C20: 2331 | D20: 19 | F20: MLB | G20: 19 | H20: 11685 | I20: FHP | J20: Canal #2Job# 6227 | K20: Canal #2 | L20: 6227 | M20: Vulcan Pershing | P20: 1 | Q20: 199.5 | R20: 199.5 | S20: =IFERROR(_xlfn.XLOOKUP(tbl_Facturas[[#This Row],[Key_Fact]],tbl_Manifiestos[Key_Manif],tbl_Manifiestos[Pagado a Broker],0),0) -> 0 | T20: 10163.93
A21: 20-1-2025 | B21: =tbl_Facturas[[#This Row],[Factura]] & "|" & tbl_Facturas[[#This Row],[Proyecto OK]] & "|" & TEXT(tbl_Facturas[[#This Row],[Horas o Viaje]],"0.00") & "|" & TEXT(tbl_Facturas[[#This Row],[Costo unitario]],"0.00") -> 2331|Canal #2 |1.00|199.50 | C21: 2331 | D21: 19 | F21: MLB | G21: 19 | H21: 11686 | I21: FHP | J21: Canal #2Job# 6227 | K21: Canal #2 | L21: 6227 | M21: Vulcan Pershing | P21: 1 | Q21: 199.5 | R21: 199.5 | S21: =IFERROR(_xlfn.XLOOKUP(tbl_Facturas[[#This Row],[Key_Fact]],tbl_Manifiestos[Key_Manif],tbl_Manifiestos[Pagado a Broker],0),0) -> 0 | T21: 10363.43
A22: 20-1-2025 | B22: =tbl_Facturas[[#This Row],[Factura]] & "|" & tbl_Facturas[[#This Row],[Proyecto OK]] & "|" & TEXT(tbl_Facturas[[#This Row],[Horas o Viaje]],"0.00") & "|" & TEXT(tbl_Facturas[[#This Row],[Costo unitario]],"0.00") -> 2331||0.00|0.00 | C22: 2331 | G22: Discount | I22: FHP | R22: -20.54 | S22: =IFERROR(_xlfn.XLOOKUP(tbl_Facturas[[#This Row],[Key_Fact]],tbl_Manifiestos[Key_Manif],tbl_Manifiestos[Pagado a Broker],0),0) -> 0 | T22: 10342.89
A23: 20-1-2025 | B23: =tbl_Facturas[[#This Row],[Factura]] & "|" & tbl_Facturas[[#This Row],[Proyecto OK]] & "|" & TEXT(tbl_Facturas[[#This Row],[Horas o Viaje]],"0.00") & "|" & TEXT(tbl_Facturas[[#This Row],[Costo unitario]],"0.00") -> 2332|Lead Service Replacement Project|7.50|115.50 | C23: 2332 | D23: 198 | E23: POSADA | G23: 198 | H23: 11451 | I23: Millenium | J23: Lead Service Replacement Project | K23: Lead Service Replacement Project | P23: 7.5 | Q23: 115.5 | R23: 866.25 | S23: =IFERROR(_xlfn.XLOOKUP(tbl_Facturas[[#This Row],[Key_Fact]],tbl_Manifiestos[Key_Manif],tbl_Manifiestos[Pagado a Broker],0),0) -> 805.6125 | T23: 11209.14
A24: 20-1-2025 | B24: =tbl_Facturas[[#This Row],[Factura]] & "|" & tbl_Facturas[[#This Row],[Proyecto OK]] & "|" & TEXT(tbl_Facturas[[#This Row],[Horas o Viaje]],"0.00") & "|" & TEXT(tbl_Facturas[[#This Row],[Costo unitario]],"0.00") -> 2332|Lead Service Replacement Project|8.00|115.50 | C24: 2332 | D24: 515 | E24: LT | G24: 515 | H24: 12166 | I24: Millenium | J24: Lead Service Replacement Project | K24: Lead Service Replacement Project | P24: 8 | Q24: 115.5 | R24: 924 | S24: =IFERROR(_xlfn.XLOOKUP(tbl_Facturas[[#This Row],[Key_Fact]],tbl_Manifiestos[Key_Manif],tbl_Manifiestos[Pagado a Broker],0),0) -> 859.32 | T24: 12133.14
A25: 20-1-2025 | B25: =tbl_Facturas[[#This Row],[Factura]] & "|" & tbl_Facturas[[#This Row],[Proyecto OK]] & "|" & TEXT(tbl_Facturas[[#This Row],[Horas o Viaje]],"0.00") & "|" & TEXT(tbl_Facturas[[#This Row],[Costo unitario]],"0.00") -> 2332|Lead Service Replacement Project|8.00|115.50 | C25: 2332 | D25: 11 | E25: MLB | G25: 11 | H25: 11707 | I25: Millenium | J25: Lead Service Replacement Project | K25: Lead Service Replacement Project | P25: 8 | Q25: 115.5 | R25: 924 | S25: =IFERROR(_xlfn.XLOOKUP(tbl_Facturas[[#This Row],[Key_Fact]],tbl_Manifiestos[Key_Manif],tbl_Manifiestos[Pagado a Broker],0),0) -> 859.32 | T25: 13057.14
A26: 20-1-2025 | B26: =tbl_Facturas[[#This Row],[Factura]] & "|" & tbl_Facturas[[#This Row],[Proyecto OK]] & "|" & TEXT(tbl_Facturas[[#This Row],[Horas o Viaje]],"0.00") & "|" & TEXT(tbl_Facturas[[#This Row],[Costo unitario]],"0.00") -> 2332|Lead Service Replacement Project|7.50|115.50 | C26: 2332 | D26: 114 | E26: LT | G26: 114 | H26: 11961 | I26: Millenium | J26: Lead Service Replacement Project | K26: Lead Service Replacement Project | P26: 7.5 | Q26: 115.5 | R26: 866.25 | S26: =IFERROR(_xlfn.XLOOKUP(tbl_Facturas[[#This Row],[Key_Fact]],tbl_Manifiestos[Key_Manif],tbl_Manifiestos[Pagado a Broker],0),0) -> 805.6125 | T26: 13923.39
A27: 20-1-2025 | B27: =tbl_Facturas[[#This Row],[Factura]] & "|" & tbl_Facturas[[#This Row],[Proyecto OK]] & "|" & TEXT(tbl_Facturas[[#This Row],[Horas o Viaje]],"0.00") & "|" & TEXT(tbl_Facturas[[#This Row],[Costo unitario]],"0.00") -> 2333|Lead Replacement Service|10.00|110.00 | C27: 2333 | D27: 67 | E27: LT | G27: 67 | H27: 11613 | I27: PanOceanic | J27: 3347 | K27: Lead Replacement Service | L27: 3347 | P27: 10 | Q27: 110 | R27: 1100 | S27: =IFERROR(_xlfn.XLOOKUP(tbl_Facturas[[#This Row],[Key_Fact]],tbl_Manifiestos[Key_Manif],tbl_Manifiestos[Pagado a Broker],0),0) -> 1023 | T27: 15023.39
A28: 20-1-2025 | B28: =tbl_Facturas[[#This Row],[Factura]] & "|" & tbl_Facturas[[#This Row],[Proyecto OK]] & "|" & TEXT(tbl_Facturas[[#This Row],[Horas o Viaje]],"0.00") & "|" & TEXT(tbl_Facturas[[#This Row],[Costo unitario]],"0.00") -> 2333|Lead Replacement Service|10.00|110.00 | C28: 2333 | D28: 617 | E28: LT | G28: 617 | H28: 10565 | I28: PanOceanic | J28: 3347 | K28: Lead Replacement Service | L28: 3347 | P28: 10 | Q28: 110 | R28: 1100 | S28: =IFERROR(_xlfn.XLOOKUP(tbl_Facturas[[#This Row],[Key_Fact]],tbl_Manifiestos[Key_Manif],tbl_Manifiestos[Pagado a Broker],0),0) -> 1023 | T28: 16123.39
A29: 20-1-2025 | B29: =tbl_Facturas[[#This Row],[Factura]] & "|" & tbl_Facturas[[#This Row],[Proyecto OK]] & "|" & TEXT(tbl_Facturas[[#This Row],[Horas o Viaje]],"0.00") & "|" & TEXT(tbl_Facturas[[#This Row],[Costo unitario]],"0.00") -> 2333|Lead Replacement Service|16.00|110.00 | C29: 2333 | D29: 73 | E29: LI | G29: 73 | H29: 11995 | I29: PanOceanic | J29: 3347 | K29: Lead Replacement Service | L29: 3347 | P29: 16 | Q29: 110 | R29: 1760 | S29: =IFERROR(_xlfn.XLOOKUP(tbl_Facturas[[#This Row],[Key_Fact]],tbl_Manifiestos[Key_Manif],tbl_Manifiestos[Pagado a Broker],0),0) -> 0 | T29: 17883.39
A30: 20-1-2025 | B30: =tbl_Facturas[[#This Row],[Factura]] & "|" & tbl_Facturas[[#This Row],[Proyecto OK]] & "|" & TEXT(tbl_Facturas[[#This Row],[Horas o Viaje]],"0.00") & "|" & TEXT(tbl_Facturas[[#This Row],[Costo unitario]],"0.00") -> 2333|Lead Replacement Service|13.00|110.00 | C30: 2333 | D30: 617 | E30: LT | G30: 617 | H30: 10566 | I30: PanOceanic | J30: 3347 | K30: Lead Replacement Service | L30: 3347 | P30: 13 | Q30: 110 | R30: 1430 | S30: =IFERROR(_xlfn.XLOOKUP(tbl_Facturas[[#This Row],[Key_Fact]],tbl_Manifiestos[Key_Manif],tbl_Manifiestos[Pagado a Broker],0),0) -> 1329.9 | T30: 19313.39
A31: 20-1-2025 | B31: =tbl_Facturas[[#This Row],[Factura]] & "|" & tbl_Facturas[[#This Row],[Proyecto OK]] & "|" & TEXT(tbl_Facturas[[#This Row],[Horas o Viaje]],"0.00") & "|" & TEXT(tbl_Facturas[[#This Row],[Costo unitario]],"0.00") -> 2333|Lead Replacement Service|10.00|110.00 | C31: 2333 | D31: 617 | E31: LT | G31: 617 | H31: 10567 | I31: PanOceanic | J31: 3347 | K31: Lead Replacement Service | L31: 3347 | P31: 10 | Q31: 110 | R31: 1100 | S31: =IFERROR(_xlfn.XLOOKUP(tbl_Facturas[[#This Row],[Key_Fact]],tbl_Manifiestos[Key_Manif],tbl_Manifiestos[Pagado a Broker],0),0) -> 1023 | T31: 20413.39
A32: 20-1-2025 | B32: =tbl_Facturas[[#This Row],[Factura]] & "|" & tbl_Facturas[[#This Row],[Proyecto OK]] & "|" & TEXT(tbl_Facturas[[#This Row],[Horas o Viaje]],"0.00") & "|" & TEXT(tbl_Facturas[[#This Row],[Costo unitario]],"0.00") -> 2334|Lead Service Line Replacements|10.50|115.00 | C32: 2334 | D32: 308 | E32: AAA | G32: 308 | H32: 11108 | I32: Plumbing | J32: Lead Service Line Replacements | K32: Lead Service Line Replacements | P32: 10.5 | Q32: 115 | R32: 1207.5 | S32: =IFERROR(_xlfn.XLOOKUP(tbl_Facturas[[#This Row],[Key_Fact]],tbl_Manifiestos[Key_Manif],tbl_Manifiestos[Pagado a Broker],0),0) -> 1122.975 | T32: 21620.89
A33: 20-1-2025 | B33: =tbl_Facturas[[#This Row],[Factura]] & "|" & tbl_Facturas[[#This Row],[Proyecto OK]] & "|" & TEXT(tbl_Facturas[[#This Row],[Horas o Viaje]],"0.00") & "|" & TEXT(tbl_Facturas[[#This Row],[Costo unitario]],"0.00") -> 2334|Lead Service Line Replacements|9.00|115.00 | C33: 2334 | D33: 198 | E33: POSADA | G33: 198 | H33: 11452 | I33: Plumbing | J33: Lead Service Line Replacements | K33: Lead Service Line Replacements | P33: 9 | Q33: 115 | R33: 1035 | S33: =IFERROR(_xlfn.XLOOKUP(tbl_Facturas[[#This Row],[Key_Fact]],tbl_Manifiestos[Key_Manif],tbl_Manifiestos[Pagado a Broker],0),0) -> 962.55 | T33: 22655.89
A34: 20-1-2025 | B34: =tbl_Facturas[[#This Row],[Factura]] & "|" & tbl_Facturas[[#This Row],[Proyecto OK]] & "|" & TEXT(tbl_Facturas[[#This Row],[Horas o Viaje]],"0.00") & "|" & TEXT(tbl_Facturas[[#This Row],[Costo unitario]],"0.00") -> 2334|Lead Service Line Replacements|8.00|115.00 | C34: 2334 | D34: 19 | E34: MLB | G34: 19 | H34: 11687 | I34: Plumbing | J34: Lead Service Line Replacements | K34: Lead Service Line Replacements | P34: 8 | Q34: 115 | R34: 920 | S34: =IFERROR(_xlfn.XLOOKUP(tbl_Facturas[[#This Row],[Key_Fact]],tbl_Manifiestos[Key_Manif],tbl_Manifiestos[Pagado a Broker],0),0) -> 855.6 | T34: 23575.89
A35: 20-1-2025 | B35: =tbl_Facturas[[#This Row],[Factura]] & "|" & tbl_Facturas[[#This Row],[Proyecto OK]] & "|" & TEXT(tbl_Facturas[[#This Row],[Horas o Viaje]],"0.00") & "|" & TEXT(tbl_Facturas[[#This Row],[Costo unitario]],"0.00") -> 2334|Lead Service Line Replacements|8.00|115.00 | C35: 2334 | D35: 308 | E35: AAA | G35: 308 | H35: 11107 | I35: Plumbing | J35: Lead Service Line Replacements | K35: Lead Service Line Replacements | P35: 8 | Q35: 115 | R35: 920 | S35: =IFERROR(_xlfn.XLOOKUP(tbl_Facturas[[#This Row],[Key_Fact]],tbl_Manifiestos[Key_Manif],tbl_Manifiestos[Pagado a Broker],0),0) -> 855.6 | T35: 24495.89
A36: 20-1-2025 | B36: =tbl_Facturas[[#This Row],[Factura]] & "|" & tbl_Facturas[[#This Row],[Proyecto OK]] & "|" & TEXT(tbl_Facturas[[#This Row],[Horas o Viaje]],"0.00") & "|" & TEXT(tbl_Facturas[[#This Row],[Costo unitario]],"0.00") -> 2334|Lead Service Line Replacements|8.00|115.00 | C36: 2334 | D36: 325 | E36: LT | G36: 325 | H36: 11381 | I36: Plumbing | J36: Lead Service Line Replacements | K36: Lead Service Line Replacements | P36: 8 | Q36: 115 | R36: 920 | S36: =IFERROR(_xlfn.XLOOKUP(tbl_Facturas[[#This Row],[Key_Fact]],tbl_Manifiestos[Key_Manif],tbl_Manifiestos[Pagado a Broker],0),0) -> 855.6 | T36: 25415.89
A37: 20-1-2025 | B37: =tbl_Facturas[[#This Row],[Factura]] & "|" & tbl_Facturas[[#This Row],[Proyecto OK]] & "|" & TEXT(tbl_Facturas[[#This Row],[Horas o Viaje]],"0.00") & "|" & TEXT(tbl_Facturas[[#This Row],[Costo unitario]],"0.00") -> 2334|Lead Service Line Replacements|8.00|115.00 | C37: 2334 | D37: 198 | E37: POSADA | G37: 198 | H37: 11453 | I37: Plumbing | J37: Lead Service Line Replacements | K37: Lead Service Line Replacements | P37: 8 | Q37: 115 | R37: 920 | S37: =IFERROR(_xlfn.XLOOKUP(tbl_Facturas[[#This Row],[Key_Fact]],tbl_Manifiestos[Key_Manif],tbl_Manifiestos[Pagado a Broker],0),0) -> 855.6 | T37: 26335.89
A38: 27-1-2025 | B38: =tbl_Facturas[[#This Row],[Factura]] & "|" & tbl_Facturas[[#This Row],[Proyecto OK]] & "|" & TEXT(tbl_Facturas[[#This Row],[Horas o Viaje]],"0.00") & "|" & TEXT(tbl_Facturas[[#This Row],[Costo unitario]],"0.00") -> 2335|Canal #2 |1.00|199.50 | C38: 2335 | D38: 67 | F38: LT | G38: 67 | H38: 11619 | I38: FHP | J38: Canal #2Job# 6227 | K38: Canal #2 | L38: 6227 | M38: Vulcan Pershing | P38: 1 | Q38: 199.5 | R38: 199.5 | S38: =IFERROR(_xlfn.XLOOKUP(tbl_Facturas[[#This Row],[Key_Fact]],tbl_Manifiestos[Key_Manif],tbl_Manifiestos[Pagado a Broker],0),0) -> 0 | T38: 26535.39
A39: 27-1-2025 | B39: =tbl_Facturas[[#This Row],[Factura]] & "|" & tbl_Facturas[[#This Row],[Proyecto OK]] & "|" & TEXT(tbl_Facturas[[#This Row],[Horas o Viaje]],"0.00") & "|" & TEXT(tbl_Facturas[[#This Row],[Costo unitario]],"0.00") -> 2335|Canal #2 |1.00|199.50 | C39: 2335 | D39: 67 | F39: LT | G39: 67 | H39: 11620 | I39: FHP | J39: Canal #2Job# 6227 | K39: Canal #2 | L39: 6227 | M39: Vulcan Pershing | P39: 1 | Q39: 199.5 | R39: 199.5 | S39: =IFERROR(_xlfn.XLOOKUP(tbl_Facturas[[#This Row],[Key_Fact]],tbl_Manifiestos[Key_Manif],tbl_Manifiestos[Pagado a Broker],0),0) -> 0 | T39: 26734.89
A40: 27-1-2025 | B40: =tbl_Facturas[[#This Row],[Factura]] & "|" & tbl_Facturas[[#This Row],[Proyecto OK]] & "|" & TEXT(tbl_Facturas[[#This Row],[Horas o Viaje]],"0.00") & "|" & TEXT(tbl_Facturas[[#This Row],[Costo unitario]],"0.00") -> 2335|Canal #2 |1.00|199.50 | C40: 2335 | D40: 67 | F40: LT | G40: 67 | H40: 11621 | I40: FHP | J40: Canal #2Job# 6227 | K40: Canal #2 | L40: 6227 | M40: Vulcan Pershing | P40: 1 | Q40: 199.5 | R40: 199.5 | S40: =IFERROR(_xlfn.XLOOKUP(tbl_Facturas[[#This Row],[Key_Fact]],tbl_Manifiestos[Key_Manif],tbl_Manifiestos[Pagado a Broker],0),0) -> 0 | T40: 26934.39
A41: 27-1-2025 | B41: =tbl_Facturas[[#This Row],[Factura]] & "|" & tbl_Facturas[[#This Row],[Proyecto OK]] & "|" & TEXT(tbl_Facturas[[#This Row],[Horas o Viaje]],"0.00") & "|" & TEXT(tbl_Facturas[[#This Row],[Costo unitario]],"0.00") -> 2335|Canal #2 |1.00|199.50 | C41: 2335 | D41: 67 | F41: LT | G41: 67 | H41: 11623 | I41: FHP | J41: Canal #2Job# 6227 | K41: Canal #2 | L41: 6227 | M41: Vulcan Pershing | P41: 1 | Q41: 199.5 | R41: 199.5 | S41: =IFERROR(_xlfn.XLOOKUP(tbl_Facturas[[#This Row],[Key_Fact]],tbl_Manifiestos[Key_Manif],tbl_Manifiestos[Pagado a Broker],0),0) -> 0 | T41: 27133.89
A42: 27-1-2025 | B42: =tbl_Facturas[[#This Row],[Factura]] & "|" & tbl_Facturas[[#This Row],[Proyecto OK]] & "|" & TEXT(tbl_Facturas[[#This Row],[Horas o Viaje]],"0.00") & "|" & TEXT(tbl_Facturas[[#This Row],[Costo unitario]],"0.00") -> 2335|Canal #2 |1.00|199.50 | C42: 2335 | D42: 67 | F42: LT | G42: 67 | H42: 11624 | I42: FHP | J42: Canal #2Job# 6227 | K42: Canal #2 | L42: 6227 | M42: Vulcan Pershing | P42: 1 | Q42: 199.5 | R42: 199.5 | S42: =IFERROR(_xlfn.XLOOKUP(tbl_Facturas[[#This Row],[Key_Fact]],tbl_Manifiestos[Key_Manif],tbl_Manifiestos[Pagado a Broker],0),0) -> 0 | T42: 27333.39
A43: 27-1-2025 | B43: =tbl_Facturas[[#This Row],[Factura]] & "|" & tbl_Facturas[[#This Row],[Proyecto OK]] & "|" & TEXT(tbl_Facturas[[#This Row],[Horas o Viaje]],"0.00") & "|" & TEXT(tbl_Facturas[[#This Row],[Costo unitario]],"0.00") -> 2335|Canal #2 |1.00|199.50 | C43: 2335 | D43: 67 | F43: LT | G43: 67 | H43: 11625 | I43: FHP | J43: Canal #2Job# 6227 | K43: Canal #2 | L43: 6227 | M43: Vulcan Pershing | P43: 1 | Q43: 199.5 | R43: 199.5 | S43: =IFERROR(_xlfn.XLOOKUP(tbl_Facturas[[#This Row],[Key_Fact]],tbl_Manifiestos[Key_Manif],tbl_Manifiestos[Pagado a Broker],0),0) -> 0 | T43: 27532.89
A44: 27-1-2025 | B44: =tbl_Facturas[[#This Row],[Factura]] & "|" & tbl_Facturas[[#This Row],[Proyecto OK]] & "|" & TEXT(tbl_Facturas[[#This Row],[Horas o Viaje]],"0.00") & "|" & TEXT(tbl_Facturas[[#This Row],[Costo unitario]],"0.00") -> 2335|Canal #2 |1.00|56.50 | C44: 2335 | D44: 67 | F44: LT | G44: 67 | H44: 11619 | I44: FHP | J44: Canal #2Job# 6227 | K44: Canal #2 | L44: 6227 | M44: Pershing Recycle | N44: 14668757 | O44: CA1 | P44: 1 | Q44: 56.5 | R44: 56.5 | S44: =IFERROR(_xlfn.XLOOKUP(tbl_Facturas[[#This Row],[Key_Fact]],tbl_Manifiestos[Key_Manif],tbl_Manifiestos[Pagado a Broker],0),0) -> 0 | T44: 27589.39
A45: 27-1-2025 | B45: =tbl_Facturas[[#This Row],[Factura]] & "|" & tbl_Facturas[[#This Row],[Proyecto OK]] & "|" & TEXT(tbl_Facturas[[#This Row],[Horas o Viaje]],"0.00") & "|" & TEXT(tbl_Facturas[[#This Row],[Costo unitario]],"0.00") -> 2335|Canal #2 |1.00|56.50 | C45: 2335 | D45: 67 | F45: LT | G45: 67 | H45: 11620 | I45: FHP | J45: Canal #2Job# 6227 | K45: Canal #2 | L45: 6227 | M45: Pershing Recycle | N45: 14668760 | O45: CA1 | P45: 1 | Q45: 56.5 | R45: 56.5 | S45: =IFERROR(_xlfn.XLOOKUP(tbl_Facturas[[#This Row],[Key_Fact]],tbl_Manifiestos[Key_Manif],tbl_Manifiestos[Pagado a Broker],0),0) -> 0 | T45: 27645.89
A46: 27-1-2025 | B46: =tbl_Facturas[[#This Row],[Factura]] & "|" & tbl_Facturas[[#This Row],[Proyecto OK]] & "|" & TEXT(tbl_Facturas[[#This Row],[Horas o Viaje]],"0.00") & "|" & TEXT(tbl_Facturas[[#This Row],[Costo unitario]],"0.00") -> 2335|Canal #2 |1.00|56.50 | C46: 2335 | D46: 67 | F46: LT | G46: 67 | H46: 11621 | I46: FHP | J46: Canal #2Job# 6227 | K46: Canal #2 | L46: 6227 | M46: Pershing Recycle | N46: 14668762 | O46: CA1 | P46: 1 | Q46: 56.5 | R46: 56.5 | S46: =IFERROR(_xlfn.XLOOKUP(tbl_Facturas[[#This Row],[Key_Fact]],tbl_Manifiestos[Key_Manif],tbl_Manifiestos[Pagado a Broker],0),0) -> 0 | T46: 27702.39
A47: 27-1-2025 | B47: =tbl_Facturas[[#This Row],[Factura]] & "|" & tbl_Facturas[[#This Row],[Proyecto OK]] & "|" & TEXT(tbl_Facturas[[#This Row],[Horas o Viaje]],"0.00") & "|" & TEXT(tbl_Facturas[[#This Row],[Costo unitario]],"0.00") -> 2335|Canal #2 |1.00|56.50 | C47: 2335 | D47: 67 | F47: LT | G47: 67 | H47: 11623 | I47: FHP | J47: Canal #2Job# 6227 | K47: Canal #2 | L47: 6227 | M47: Pershing Recycle | N47: 14668766 | O47: CA1 | P47: 1 | Q47: 56.5 | R47: 56.5 | S47: =IFERROR(_xlfn.XLOOKUP(tbl_Facturas[[#This Row],[Key_Fact]],tbl_Manifiestos[Key_Manif],tbl_Manifiestos[Pagado a Broker],0),0) -> 0 | T47: 27758.89
A48: 27-1-2025 | B48: =tbl_Facturas[[#This Row],[Factura]] & "|" & tbl_Facturas[[#This Row],[Proyecto OK]] & "|" & TEXT(tbl_Facturas[[#This Row],[Horas o Viaje]],"0.00") & "|" & TEXT(tbl_Facturas[[#This Row],[Costo unitario]],"0.00") -> 2335|Canal #2 |1.00|56.50 | C48: 2335 | D48: 67 | F48: LT | G48: 67 | H48: 11624 | I48: FHP | J48: Canal #2Job# 6227 | K48: Canal #2 | L48: 6227 | M48: Pershing Recycle | N48: 14668772 | O48: CA1 | P48: 1 | Q48: 56.5 | R48: 56.5 | S48: =IFERROR(_xlfn.XLOOKUP(tbl_Facturas[[#This Row],[Key_Fact]],tbl_Manifiestos[Key_Manif],tbl_Manifiestos[Pagado a Broker],0),0) -> 0 | T48: 27815.39
A49: 27-1-2025 | B49: =tbl_Facturas[[#This Row],[Factura]] & "|" & tbl_Facturas[[#This Row],[Proyecto OK]] & "|" & TEXT(tbl_Facturas[[#This Row],[Horas o Viaje]],"0.00") & "|" & TEXT(tbl_Facturas[[#This Row],[Costo unitario]],"0.00") -> 2335|Canal #2 |1.00|56.50 | C49: 2335 | D49: 67 | F49: LT | G49: 67 | H49: 11625 | I49: FHP | J49: Canal #2Job# 6227 | K49: Canal #2 | L49: 6227 | M49: Pershing Recycle | N49: 14668778 | O49: CA1 | P49: 1 | Q49: 56.5 | R49: 56.5 | S49: =IFERROR(_xlfn.XLOOKUP(tbl_Facturas[[#This Row],[Key_Fact]],tbl_Manifiestos[Key_Manif],tbl_Manifiestos[Pagado a Broker],0),0) -> 0 | T49: 27871.89
A50: 27-1-2025 | B50: =tbl_Facturas[[#This Row],[Factura]] & "|" & tbl_Facturas[[#This Row],[Proyecto OK]] & "|" & TEXT(tbl_Facturas[[#This Row],[Horas o Viaje]],"0.00") & "|" & TEXT(tbl_Facturas[[#This Row],[Costo unitario]],"0.00") -> 2335||0.00|0.00 | C50: 2335 | G50: Discount | I50: FHP | R50: -0.36 | S50: =IFERROR(_xlfn.XLOOKUP(tbl_Facturas[[#This Row],[Key_Fact]],tbl_Manifiestos[Key_Manif],tbl_Manifiestos[Pagado a Broker],0),0) -> 0 | T50: 27871.53
A51: 27-1-2025 | B51: =tbl_Facturas[[#This Row],[Factura]] & "|" & tbl_Facturas[[#This Row],[Proyecto OK]] & "|" & TEXT(tbl_Facturas[[#This Row],[Horas o Viaje]],"0.00") & "|" & TEXT(tbl_Facturas[[#This Row],[Costo unitario]],"0.00") -> 2336|Lead Service Replacement Project|6.50|115.50 | C51: 2336 | D51: 325 | E51: LT | G51: 325 | H51: 11394 | I51: Millenium | J51: Lead Service Replacement Project | K51: Lead Service Replacement Project | P51: 6.5 | Q51: 115.5 | R51: 750.75 | S51: =IFERROR(_xlfn.XLOOKUP(tbl_Facturas[[#This Row],[Key_Fact]],tbl_Manifiestos[Key_Manif],tbl_Manifiestos[Pagado a Broker],0),0) -> 698.1975 | T51: 28622.28
A52: 27-1-2025 | B52: =tbl_Facturas[[#This Row],[Factura]] & "|" & tbl_Facturas[[#This Row],[Proyecto OK]] & "|" & TEXT(tbl_Facturas[[#This Row],[Horas o Viaje]],"0.00") & "|" & TEXT(tbl_Facturas[[#This Row],[Costo unitario]],"0.00") -> 2336|Lead Service Replacement Project|9.50|115.50 | C52: 2336 | D52: 73 | E52: LI | G52: 73 | H52: 12005 | I52: Millenium | J52: Lead Service Replacement Project | K52: Lead Service Replacement Project | P52: 9.5 | Q52: 115.5 | R52: 1097.25 | S52: =IFERROR(_xlfn.XLOOKUP(tbl_Facturas[[#This Row],[Key_Fact]],tbl_Manifiestos[Key_Manif],tbl_Manifiestos[Pagado a Broker],0),0) -> 0 | T52: 29719.53
A53: 27-1-2025 | B53: =tbl_Facturas[[#This Row],[Factura]] & "|" & tbl_Facturas[[#This Row],[Proyecto OK]] & "|" & TEXT(tbl_Facturas[[#This Row],[Horas o Viaje]],"0.00") & "|" & TEXT(tbl_Facturas[[#This Row],[Costo unitario]],"0.00") -> 2336|Lead Service Replacement Project|8.00|115.50 | C53: 2336 | D53: 11 | E53: MLB | G53: 11 | H53: 10821 | I53: Millenium | J53: Lead Service Replacement Project | K53: Lead Service Replacement Project | P53: 8 | Q53: 115.5 | R53: 924 | S53: =IFERROR(_xlfn.XLOOKUP(tbl_Facturas[[#This Row],[Key_Fact]],tbl_Manifiestos[Key_Manif],tbl_Manifiestos[Pagado a Broker],0),0) -> 859.32 | T53: 30643.53
A54: 27-1-2025 | B54: =tbl_Facturas[[#This Row],[Factura]] & "|" & tbl_Facturas[[#This Row],[Proyecto OK]] & "|" & TEXT(tbl_Facturas[[#This Row],[Horas o Viaje]],"0.00") & "|" & TEXT(tbl_Facturas[[#This Row],[Costo unitario]],"0.00") -> 2337|Arquilla Park|8.50|110.00 | C54: 2337 | D54: 198 | E54: POSADA | G54: 198 | H54: 11454 | I54: PanOceanic | K54: Arquilla Park | P54: 8.5 | Q54: 110 | R54: 935 | S54: =IFERROR(_xlfn.XLOOKUP(tbl_Facturas[[#This Row],[Key_Fact]],tbl_Manifiestos[Key_Manif],tbl_Manifiestos[Pagado a Broker],0),0) -> 869.55 | T54: 31578.53
A55: 27-1-2025 | B55: =tbl_Facturas[[#This Row],[Factura]] & "|" & tbl_Facturas[[#This Row],[Proyecto OK]] & "|" & TEXT(tbl_Facturas[[#This Row],[Horas o Viaje]],"0.00") & "|" & TEXT(tbl_Facturas[[#This Row],[Costo unitario]],"0.00") -> 2337|Arquilla Park|9.00|110.00 | C55: 2337 | D55: 19 | E55: MLB | G55: 19 | H55: 11681 | I55: PanOceanic | K55: Arquilla Park | P55: 9 | Q55: 110 | R55: 990 | S55: =IFERROR(_xlfn.XLOOKUP(tbl_Facturas[[#This Row],[Key_Fact]],tbl_Manifiestos[Key_Manif],tbl_Manifiestos[Pagado a Broker],0),0) -> 0 | T55: 32568.53
A56: 27-1-2025 | B56: =tbl_Facturas[[#This Row],[Factura]] & "|" & tbl_Facturas[[#This Row],[Proyecto OK]] & "|" & TEXT(tbl_Facturas[[#This Row],[Horas o Viaje]],"0.00") & "|" & TEXT(tbl_Facturas[[#This Row],[Costo unitario]],"0.00") -> 2338|Lead Replacement Service|9.00|110.00 | C56: 2338 | D56: 617 | E56: LT | G56: 617 | H56: 10568 | I56: PanOceanic | J56: 3347 | K56: Lead Replacement Service | L56: 3347 | P56: 9 | Q56: 110 | R56: 990 | S56: =IFERROR(_xlfn.XLOOKUP(tbl_Facturas[[#This Row],[Key_Fact]],tbl_Manifiestos[Key_Manif],tbl_Manifiestos[Pagado a Broker],0),0) -> 920.7 | T56: 33558.53
A57: 27-1-2025 | B57: =tbl_Facturas[[#This Row],[Factura]] & "|" & tbl_Facturas[[#This Row],[Proyecto OK]] & "|" & TEXT(tbl_Facturas[[#This Row],[Horas o Viaje]],"0.00") & "|" & TEXT(tbl_Facturas[[#This Row],[Costo unitario]],"0.00") -> 2338|Lead Replacement Service|10.25|110.00 | C57: 2338 | D57: 515 | E57: LT | G57: 515 | H57: 11347 | I57: PanOceanic | J57: 3347 | K57: Lead Replacement Service | L57: 3347 | P57: 10.25 | Q57: 110 | R57: 1127.5 | S57: =IFERROR(_xlfn.XLOOKUP(tbl_Facturas[[#This Row],[Key_Fact]],tbl_Manifiestos[Key_Manif],tbl_Manifiestos[Pagado a Broker],0),0) -> 0 | T57: 34686.03
A58: 3-2-2025 | B58: =tbl_Facturas[[#This Row],[Factura]] & "|" & tbl_Facturas[[#This Row],[Proyecto OK]] & "|" & TEXT(tbl_Facturas[[#This Row],[Horas o Viaje]],"0.00") & "|" & TEXT(tbl_Facturas[[#This Row],[Costo unitario]],"0.00") -> 2339|Lead Service Replacement|3.00|120.00 | C58: 2339 | D58: 67 | E58: LT | G58: 67 | H58: 11627 | I58: Benchmark | J58: 2332-01Lead Service Replacement | K58: Lead Service Replacement | L58: 2332-01 | P58: 3 | Q58: 120 | R58: 360 | S58: =IFERROR(_xlfn.XLOOKUP(tbl_Facturas[[#This Row],[Key_Fact]],tbl_Manifiestos[Key_Manif],tbl_Manifiestos[Pagado a Broker],0),0) -> 334.8 | T58: 35046.03
A59: 3-2-2025 | B59: =tbl_Facturas[[#This Row],[Factura]] & "|" & tbl_Facturas[[#This Row],[Proyecto OK]] & "|" & TEXT(tbl_Facturas[[#This Row],[Horas o Viaje]],"0.00") & "|" & TEXT(tbl_Facturas[[#This Row],[Costo unitario]],"0.00") -> 2339|Lead Service Replacement|10.50|120.00 | C59: 2339 | D59: 73 | E59: LI | G59: 73 | H59: 11996 | I59: Benchmark | J59: 2332-01Lead Service Replacement | K59: Lead Service Replacement | L59: 2332-01 | P59: 10.5 | Q59: 120 | R59: 1260 | S59: =IFERROR(_xlfn.XLOOKUP(tbl_Facturas[[#This Row],[Key_Fact]],tbl_Manifiestos[Key_Manif],tbl_Manifiestos[Pagado a Broker],0),0) -> 0 | T59: 36306.03
A60: 3-2-2025 | B60: =tbl_Facturas[[#This Row],[Factura]] & "|" & tbl_Facturas[[#This Row],[Proyecto OK]] & "|" & TEXT(tbl_Facturas[[#This Row],[Horas o Viaje]],"0.00") & "|" & TEXT(tbl_Facturas[[#This Row],[Costo unitario]],"0.00") -> 2339|Lead Service Replacement|9.50|120.00 | C60: 2339 | D60: 11 | E60: MLB | G60: 19 | H60: 11679 | I60: Benchmark | J60: 2332-01Lead Service Replacement | K60: Lead Service Replacement | L60: 2332-01 | P60: 9.5 | Q60: 120 | R60: 1140 | S60: =IFERROR(_xlfn.XLOOKUP(tbl_Facturas[[#This Row],[Key_Fact]],tbl_Manifiestos[Key_Manif],tbl_Manifiestos[Pagado a Broker],0),0) -> 1060.2 | T60: 38586.03
A61: 3-2-2025 | B61: =tbl_Facturas[[#This Row],[Factura]] & "|" & tbl_Facturas[[#This Row],[Proyecto OK]] & "|" & TEXT(tbl_Facturas[[#This Row],[Horas o Viaje]],"0.00") & "|" & TEXT(tbl_Facturas[[#This Row],[Costo unitario]],"0.00") -> 2339|Lead Service Replacement|9.50|120.00 | C61: 2339 | D61: 19 | E61: MLB | G61: 11 | H61: 11732 | I61: Benchmark | J61: 2332Lead Service Replacement | K61: Lead Service Replacement | L61: 2332 | P61: 9.5 | Q61: 120 | R61: 1140 | S61: =IFERROR(_xlfn.XLOOKUP(tbl_Facturas[[#This Row],[Key_Fact]],tbl_Manifiestos[Key_Manif],tbl_Manifiestos[Pagado a Broker],0),0) -> 1060.2 | T61: 37446.03
A62: 3-2-2025 | B62: =tbl_Facturas[[#This Row],[Factura]] & "|" & tbl_Facturas[[#This Row],[Proyecto OK]] & "|" & TEXT(tbl_Facturas[[#This Row],[Horas o Viaje]],"0.00") & "|" & TEXT(tbl_Facturas[[#This Row],[Costo unitario]],"0.00") -> 2340|Canal #2 |1.00|199.50 | C62: 2340 | D62: 108 | F62: MLB | G62: 108 | H62: 11553 | I62: FHP | J62: Canal #2Job# 6227 | K62: Canal #2 | L62: 6227 | M62: Vulcan Pershing | P62: 1 | Q62: 199.5 | R62: 199.5 | S62: =IFERROR(_xlfn.XLOOKUP(tbl_Facturas[[#This Row],[Key_Fact]],tbl_Manifiestos[Key_Manif],tbl_Manifiestos[Pagado a Broker],0),0) -> 0 | T62: 38785.53
A63: 3-2-2025 | B63: =tbl_Facturas[[#This Row],[Factura]] & "|" & tbl_Facturas[[#This Row],[Proyecto OK]] & "|" & TEXT(tbl_Facturas[[#This Row],[Horas o Viaje]],"0.00") & "|" & TEXT(tbl_Facturas[[#This Row],[Costo unitario]],"0.00") -> 2340|Canal #2 |1.00|199.50 | C63: 2340 | D63: 108 | F63: MLB | G63: 108 | H63: 11575 | I63: FHP | J63: Canal #2Job# 6227 | K63: Canal #2 | L63: 6227 | M63: Vulcan Pershing | P63: 1 | Q63: 199.5 | R63: 199.5 | S63: =IFERROR(_xlfn.XLOOKUP(tbl_Facturas[[#This Row],[Key_Fact]],tbl_Manifiestos[Key_Manif],tbl_Manifiestos[Pagado a Broker],0),0) -> 0 | T63: 38985.03
A64: 3-2-2025 | B64: =tbl_Facturas[[#This Row],[Factura]] & "|" & tbl_Facturas[[#This Row],[Proyecto OK]] & "|" & TEXT(tbl_Facturas[[#This Row],[Horas o Viaje]],"0.00") & "|" & TEXT(tbl_Facturas[[#This Row],[Costo unitario]],"0.00") -> 2340|Canal #2 |1.00|199.50 | C64: 2340 | D64: 108 | F64: MLB | G64: 108 | H64: 11577 | I64: FHP | J64: Canal #2Job# 6227 | K64: Canal #2 | L64: 6227 | M64: Vulcan Pershing | P64: 1 | Q64: 199.5 | R64: 199.5 | S64: =IFERROR(_xlfn.XLOOKUP(tbl_Facturas[[#This Row],[Key_Fact]],tbl_Manifiestos[Key_Manif],tbl_Manifiestos[Pagado a Broker],0),0) -> 0 | T64: 39184.53
A65: 3-2-2025 | B65: =tbl_Facturas[[#This Row],[Factura]] & "|" & tbl_Facturas[[#This Row],[Proyecto OK]] & "|" & TEXT(tbl_Facturas[[#This Row],[Horas o Viaje]],"0.00") & "|" & TEXT(tbl_Facturas[[#This Row],[Costo unitario]],"0.00") -> 2340|Canal #2 |1.00|199.50 | C65: 2340 | D65: 108 | F65: MLB | G65: 108 | H65: 11578 | I65: FHP | J65: Canal #2Job# 6227 | K65: Canal #2 | L65: 6227 | M65: Vulcan Pershing | P65: 1 | Q65: 199.5 | R65: 199.5 | S65: =IFERROR(_xlfn.XLOOKUP(tbl_Facturas[[#This Row],[Key_Fact]],tbl_Manifiestos[Key_Manif],tbl_Manifiestos[Pagado a Broker],0),0) -> 0 | T65: 39384.03
A66: 3-2-2025 | B66: =tbl_Facturas[[#This Row],[Factura]] & "|" & tbl_Facturas[[#This Row],[Proyecto OK]] & "|" & TEXT(tbl_Facturas[[#This Row],[Horas o Viaje]],"0.00") & "|" & TEXT(tbl_Facturas[[#This Row],[Costo unitario]],"0.00") -> 2340|Canal #2 |1.00|199.50 | C66: 2340 | D66: 108 | F66: MLB | G66: 108 | H66: 11579 | I66: FHP | J66: Canal #2Job# 6227 | K66: Canal #2 | L66: 6227 | M66: Vulcan Pershing | P66: 1 | Q66: 199.5 | R66: 199.5 | S66: =IFERROR(_xlfn.XLOOKUP(tbl_Facturas[[#This Row],[Key_Fact]],tbl_Manifiestos[Key_Manif],tbl_Manifiestos[Pagado a Broker],0),0) -> 0 | T66: 39583.53
A67: 3-2-2025 | B67: =tbl_Facturas[[#This Row],[Factura]] & "|" & tbl_Facturas[[#This Row],[Proyecto OK]] & "|" & TEXT(tbl_Facturas[[#This Row],[Horas o Viaje]],"0.00") & "|" & TEXT(tbl_Facturas[[#This Row],[Costo unitario]],"0.00") -> 2340|Canal #2 |1.00|199.50 | C67: 2340 | D67: 515 | F67: LT | G67: 515 | H67: 11750 | I67: FHP | J67: Canal #2Job# 6227 | K67: Canal #2 | L67: 6227 | M67: Vulcan Pershing | P67: 1 | Q67: 199.5 | R67: 199.5 | S67: =IFERROR(_xlfn.XLOOKUP(tbl_Facturas[[#This Row],[Key_Fact]],tbl_Manifiestos[Key_Manif],tbl_Manifiestos[Pagado a Broker],0),0) -> 0 | T67: 39783.03
A68: 3-2-2025 | B68: =tbl_Facturas[[#This Row],[Factura]] & "|" & tbl_Facturas[[#This Row],[Proyecto OK]] & "|" & TEXT(tbl_Facturas[[#This Row],[Horas o Viaje]],"0.00") & "|" & TEXT(tbl_Facturas[[#This Row],[Costo unitario]],"0.00") -> 2340|Canal #2 |1.00|199.50 | C68: 2340 | D68: 515 | F68: LT | G68: 515 | H68: 11752 | I68: FHP | J68: Canal #2Job# 6227 | K68: Canal #2 | L68: 6227 | M68: Vulcan Pershing | P68: 1 | Q68: 199.5 | R68: 199.5 | S68: =IFERROR(_xlfn.XLOOKUP(tbl_Facturas[[#This Row],[Key_Fact]],tbl_Manifiestos[Key_Manif],tbl_Manifiestos[Pagado a Broker],0),0) -> 0 | T68: 39982.53
A69: 3-2-2025 | B69: =tbl_Facturas[[#This Row],[Factura]] & "|" & tbl_Facturas[[#This Row],[Proyecto OK]] & "|" & TEXT(tbl_Facturas[[#This Row],[Horas o Viaje]],"0.00") & "|" & TEXT(tbl_Facturas[[#This Row],[Costo unitario]],"0.00") -> 2340|Canal #2 |1.00|199.50 | C69: 2340 | D69: 515 | F69: LT | G69: 515 | H69: 11768 | I69: FHP | J69: Canal #2Job# 6227 | K69: Canal #2 | L69: 6227 | M69: Vulcan Pershing | P69: 1 | Q69: 199.5 | R69: 199.5 | S69: =IFERROR(_xlfn.XLOOKUP(tbl_Facturas[[#This Row],[Key_Fact]],tbl_Manifiestos[Key_Manif],tbl_Manifiestos[Pagado a Broker],0),0) -> 0 | T69: 40182.03
A70: 3-2-2025 | B70: =tbl_Facturas[[#This Row],[Factura]] & "|" & tbl_Facturas[[#This Row],[Proyecto OK]] & "|" & TEXT(tbl_Facturas[[#This Row],[Horas o Viaje]],"0.00") & "|" & TEXT(tbl_Facturas[[#This Row],[Costo unitario]],"0.00") -> 2340|Canal #2 |1.00|199.50 | C70: 2340 | D70: 515 | F70: LT | G70: 515 | H70: 11769 | I70: FHP | J70: Canal #2Job# 6227 | K70: Canal #2 | L70: 6227 | M70: Vulcan Pershing | P70: 1 | Q70: 199.5 | R70: 199.5 | S70: =IFERROR(_xlfn.XLOOKUP(tbl_Facturas[[#This Row],[Key_Fact]],tbl_Manifiestos[Key_Manif],tbl_Manifiestos[Pagado a Broker],0),0) -> 0 | T70: 40381.53
A71: 3-2-2025 | B71: =tbl_Facturas[[#This Row],[Factura]] & "|" & tbl_Facturas[[#This Row],[Proyecto OK]] & "|" & TEXT(tbl_Facturas[[#This Row],[Horas o Viaje]],"0.00") & "|" & TEXT(tbl_Facturas[[#This Row],[Costo unitario]],"0.00") -> 2340|Canal #2 |1.00|199.50 | C71: 2340 | D71: 515 | F71: LT | G71: 515 | H71: 11770 | I71: FHP | J71: Canal #2Job# 6227 | K71: Canal #2 | L71: 6227 | M71: Vulcan Pershing | P71: 1 | Q71: 199.5 | R71: 199.5 | S71: =IFERROR(_xlfn.XLOOKUP(tbl_Facturas[[#This Row],[Key_Fact]],tbl_Manifiestos[Key_Manif],tbl_Manifiestos[Pagado a Broker],0),0) -> 0 | T71: 40581.03
A72: 3-2-2025 | B72: =tbl_Facturas[[#This Row],[Factura]] & "|" & tbl_Facturas[[#This Row],[Proyecto OK]] & "|" & TEXT(tbl_Facturas[[#This Row],[Horas o Viaje]],"0.00") & "|" & TEXT(tbl_Facturas[[#This Row],[Costo unitario]],"0.00") -> 2340|Canal #2 |1.00|56.50 | C72: 2340 | D72: 108 | F72: MLB | G72: 108 | H72: 11553 | I72: FHP | J72: Canal #2Job# 6227 | K72: Canal #2 | L72: 6227 | M72: Pershing Recycle | N72: 14668786 | O72: CA1 | P72: 1 | Q72: 56.5 | R72: 56.5 | S72: =IFERROR(_xlfn.XLOOKUP(tbl_Facturas[[#This Row],[Key_Fact]],tbl_Manifiestos[Key_Manif],tbl_Manifiestos[Pagado a Broker],0),0) -> 0 | T72: 40637.53
A73: 3-2-2025 | B73: =tbl_Facturas[[#This Row],[Factura]] & "|" & tbl_Facturas[[#This Row],[Proyecto OK]] & "|" & TEXT(tbl_Facturas[[#This Row],[Horas o Viaje]],"0.00") & "|" & TEXT(tbl_Facturas[[#This Row],[Costo unitario]],"0.00") -> 2340|Canal #2 |1.00|56.50 | C73: 2340 | D73: 108 | F73: MLB | G73: 108 | H73: 11575 | I73: FHP | J73: Canal #2Job# 6227 | K73: Canal #2 | L73: 6227 | M73: Pershing Recycle | N73: 14668789 | O73: CA1 | P73: 1 | Q73: 56.5 | R73: 56.5 | S73: =IFERROR(_xlfn.XLOOKUP(tbl_Facturas[[#This Row],[Key_Fact]],tbl_Manifiestos[Key_Manif],tbl_Manifiestos[Pagado a Broker],0),0) -> 0 | T73: 40694.03
A74: 3-2-2025 | B74: =tbl_Facturas[[#This Row],[Factura]] & "|" & tbl_Facturas[[#This Row],[Proyecto OK]] & "|" & TEXT(tbl_Facturas[[#This Row],[Horas o Viaje]],"0.00") & "|" & TEXT(tbl_Facturas[[#This Row],[Costo unitario]],"0.00") -> 2340|Canal #2 |1.00|56.50 | C74: 2340 | D74: 108 | F74: MLB | G74: 108 | H74: 11577 | I74: FHP | J74: Canal #2Job# 6227 | K74: Canal #2 | L74: 6227 | M74: Pershing Recycle | N74: 14668795 | O74: CA1 | P74: 1 | Q74: 56.5 | R74: 56.5 | S74: =IFERROR(_xlfn.XLOOKUP(tbl_Facturas[[#This Row],[Key_Fact]],tbl_Manifiestos[Key_Manif],tbl_Manifiestos[Pagado a Broker],0),0) -> 0 | T74: 40750.53
A75: 3-2-2025 | B75: =tbl_Facturas[[#This Row],[Factura]] & "|" & tbl_Facturas[[#This Row],[Proyecto OK]] & "|" & TEXT(tbl_Facturas[[#This Row],[Horas o Viaje]],"0.00") & "|" & TEXT(tbl_Facturas[[#This Row],[Costo unitario]],"0.00") -> 2340|Canal #2 |1.00|56.50 | C75: 2340 | D75: 108 | F75: MLB | G75: 108 | H75: 11578 | I75: FHP | J75: Canal #2Job# 6227 | K75: Canal #2 | L75: 6227 | M75: Pershing Recycle | N75: 14668791 | O75: CA1 | P75: 1 | Q75: 56.5 | R75: 56.5 | S75: =IFERROR(_xlfn.XLOOKUP(tbl_Facturas[[#This Row],[Key_Fact]],tbl_Manifiestos[Key_Manif],tbl_Manifiestos[Pagado a Broker],0),0) -> 0 | T75: 40807.03
A76: 3-2-2025 | B76: =tbl_Facturas[[#This Row],[Factura]] & "|" & tbl_Facturas[[#This Row],[Proyecto OK]] & "|" & TEXT(tbl_Facturas[[#This Row],[Horas o Viaje]],"0.00") & "|" & TEXT(tbl_Facturas[[#This Row],[Costo unitario]],"0.00") -> 2340|Canal #2 |1.00|56.50 | C76: 2340 | D76: 108 | F76: MLB | G76: 108 | H76: 11579 | I76: FHP | J76: Canal #2Job# 6227 | K76: Canal #2 | L76: 6227 | M76: Pershing Recycle | N76: 14668793 | O76: CA1 | P76: 1 | Q76: 56.5 | R76: 56.5 | S76: =IFERROR(_xlfn.XLOOKUP(tbl_Facturas[[#This Row],[Key_Fact]],tbl_Manifiestos[Key_Manif],tbl_Manifiestos[Pagado a Broker],0),0) -> 0 | T76: 40863.53
A77: 3-2-2025 | B77: =tbl_Facturas[[#This Row],[Factura]] & "|" & tbl_Facturas[[#This Row],[Proyecto OK]] & "|" & TEXT(tbl_Facturas[[#This Row],[Horas o Viaje]],"0.00") & "|" & TEXT(tbl_Facturas[[#This Row],[Costo unitario]],"0.00") -> 2340|Canal #2 |1.00|56.50 | C77: 2340 | D77: 515 | F77: LT | G77: 515 | H77: 11750 | I77: FHP | J77: Canal #2Job# 6227 | K77: Canal #2 | L77: 6227 | M77: Pershing Recycle | N77: 14668794 | O77: CA1 | P77: 1 | Q77: 56.5 | R77: 56.5 | S77: =IFERROR(_xlfn.XLOOKUP(tbl_Facturas[[#This Row],[Key_Fact]],tbl_Manifiestos[Key_Manif],tbl_Manifiestos[Pagado a Broker],0),0) -> 0 | T77: 40920.03
A78: 3-2-2025 | B78: =tbl_Facturas[[#This Row],[Factura]] & "|" & tbl_Facturas[[#This Row],[Proyecto OK]] & "|" & TEXT(tbl_Facturas[[#This Row],[Horas o Viaje]],"0.00") & "|" & TEXT(tbl_Facturas[[#This Row],[Costo unitario]],"0.00") -> 2340|Canal #2 |1.00|56.50 | C78: 2340 | D78: 515 | F78: LT | G78: 515 | H78: 11752 | I78: FHP | J78: Canal #2Job# 6227 | K78: Canal #2 | L78: 6227 | M78: Pershing Recycle | N78: 14668788 | O78: CA1 | P78: 1 | Q78: 56.5 | R78: 56.5 | S78: =IFERROR(_xlfn.XLOOKUP(tbl_Facturas[[#This Row],[Key_Fact]],tbl_Manifiestos[Key_Manif],tbl_Manifiestos[Pagado a Broker],0),0) -> 0 | T78: 40976.53
A79: 3-2-2025 | B79: =tbl_Facturas[[#This Row],[Factura]] & "|" & tbl_Facturas[[#This Row],[Proyecto OK]] & "|" & TEXT(tbl_Facturas[[#This Row],[Horas o Viaje]],"0.00") & "|" & TEXT(tbl_Facturas[[#This Row],[Costo unitario]],"0.00") -> 2340|Canal #2 |1.00|56.50 | C79: 2340 | D79: 515 | F79: LT | G79: 515 | H79: 11768 | I79: FHP | J79: Canal #2Job# 6227 | K79: Canal #2 | L79: 6227 | M79: Pershing Recycle | N79: 14668790 | O79: CA1 | P79: 1 | Q79: 56.5 | R79: 56.5 | S79: =IFERROR(_xlfn.XLOOKUP(tbl_Facturas[[#This Row],[Key_Fact]],tbl_Manifiestos[Key_Manif],tbl_Manifiestos[Pagado a Broker],0),0) -> 0 | T79: 41033.03
A80: 3-2-2025 | B80: =tbl_Facturas[[#This Row],[Factura]] & "|" & tbl_Facturas[[#This Row],[Proyecto OK]] & "|" & TEXT(tbl_Facturas[[#This Row],[Horas o Viaje]],"0.00") & "|" & TEXT(tbl_Facturas[[#This Row],[Costo unitario]],"0.00") -> 2340|Canal #2 |1.00|56.50 | C80: 2340 | D80: 515 | F80: LT | G80: 515 | H80: 11769 | I80: FHP | J80: Canal #2Job# 6227 | K80: Canal #2 | L80: 6227 | M80: Pershing Recycle | N80: 14668792 | O80: CA1 | P80: 1 | Q80: 56.5 | R80: 56.5 | S80: =IFERROR(_xlfn.XLOOKUP(tbl_Facturas[[#This Row],[Key_Fact]],tbl_Manifiestos[Key_Manif],tbl_Manifiestos[Pagado a Broker],0),0) -> 0 | T80: 41089.53
A81: 3-2-2025 | B81: =tbl_Facturas[[#This Row],[Factura]] & "|" & tbl_Facturas[[#This Row],[Proyecto OK]] & "|" & TEXT(tbl_Facturas[[#This Row],[Horas o Viaje]],"0.00") & "|" & TEXT(tbl_Facturas[[#This Row],[Costo unitario]],"0.00") -> 2340|Canal #2 |1.00|56.50 | C81: 2340 | D81: 515 | F81: LT | G81: 515 | H81: 11770 | I81: FHP | J81: Canal #2Job# 6227 | K81: Canal #2 | L81: 6227 | M81: Pershing Recycle | N81: 14668785 | O81: CA1 | P81: 1 | Q81: 56.5 | R81: 56.5 | S81: =IFERROR(_xlfn.XLOOKUP(tbl_Facturas[[#This Row],[Key_Fact]],tbl_Manifiestos[Key_Manif],tbl_Manifiestos[Pagado a Broker],0),0) -> 0 | T81: 41146.03
A82: 3-2-2025 | B82: =tbl_Facturas[[#This Row],[Factura]] & "|" & tbl_Facturas[[#This Row],[Proyecto OK]] & "|" & TEXT(tbl_Facturas[[#This Row],[Horas o Viaje]],"0.00") & "|" & TEXT(tbl_Facturas[[#This Row],[Costo unitario]],"0.00") -> 2340||0.00|0.00 | C82: 2340 | G82: Discount | I82: FHP | R82: -0.6 | S82: =IFERROR(_xlfn.XLOOKUP(tbl_Facturas[[#This Row],[Key_Fact]],tbl_Manifiestos[Key_Manif],tbl_Manifiestos[Pagado a Broker],0),0) -> 0 | T82: 41145.43
A83: 3-2-2025 | B83: =tbl_Facturas[[#This Row],[Factura]] & "|" & tbl_Facturas[[#This Row],[Proyecto OK]] & "|" & TEXT(tbl_Facturas[[#This Row],[Horas o Viaje]],"0.00") & "|" & TEXT(tbl_Facturas[[#This Row],[Costo unitario]],"0.00") -> 2341|Lead Service Replacement Project|7.50|115.50 | C83: 2341 | D83: 19 | E83: MLB | G83: 19 | H83: 11680 | I83: Millenium | J83: Lead Service Replacement Project | K83: Lead Service Replacement Project | P83: 7.5 | Q83: 115.5 | R83: 866.25 | S83: =IFERROR(_xlfn.XLOOKUP(tbl_Facturas[[#This Row],[Key_Fact]],tbl_Manifiestos[Key_Manif],tbl_Manifiestos[Pagado a Broker],0),0) -> 805.6125 | T83: 42011.68
A84: 3-2-2025 | B84: =tbl_Facturas[[#This Row],[Factura]] & "|" & tbl_Facturas[[#This Row],[Proyecto OK]] & "|" & TEXT(tbl_Facturas[[#This Row],[Horas o Viaje]],"0.00") & "|" & TEXT(tbl_Facturas[[#This Row],[Costo unitario]],"0.00") -> 2341|Lead Service Replacement Project|10.00|115.50 | C84: 2341 | D84: 308 | E84: AAA | G84: 308 | H84: 11105 | I84: Millenium | J84: Lead Service Replacement Project | K84: Lead Service Replacement Project | P84: 10 | Q84: 115.5 | R84: 1155 | S84: =IFERROR(_xlfn.XLOOKUP(tbl_Facturas[[#This Row],[Key_Fact]],tbl_Manifiestos[Key_Manif],tbl_Manifiestos[Pagado a Broker],0),0) -> 1074.15 | T84: 43166.68
A85: 3-2-2025 | B85: =tbl_Facturas[[#This Row],[Factura]] & "|" & tbl_Facturas[[#This Row],[Proyecto OK]] & "|" & TEXT(tbl_Facturas[[#This Row],[Horas o Viaje]],"0.00") & "|" & TEXT(tbl_Facturas[[#This Row],[Costo unitario]],"0.00") -> 2341|Lead Service Replacement Project|8.75|115.50 | C85: 2341 | D85: 356 | E85: LT | G85: 356 | H85: 12012 | I85: Millenium | J85: Lead Service Replacement Project | K85: Lead Service Replacement Project | P85: 8.75 | Q85: 115.5 | R85: 1010.63 | S85: =IFERROR(_xlfn.XLOOKUP(tbl_Facturas[[#This Row],[Key_Fact]],tbl_Manifiestos[Key_Manif],tbl_Manifiestos[Pagado a Broker],0),0) -> 939.88125 | T85: 44177.31
A86: 3-2-2025 | B86: =tbl_Facturas[[#This Row],[Factura]] & "|" & tbl_Facturas[[#This Row],[Proyecto OK]] & "|" & TEXT(tbl_Facturas[[#This Row],[Horas o Viaje]],"0.00") & "|" & TEXT(tbl_Facturas[[#This Row],[Costo unitario]],"0.00") -> 2341||1.00|20.00 | C86: 2341 | G86: Discount | I86: Millenium | P86: 1 | Q86: 20 | R86: 20 | S86: =IFERROR(_xlfn.XLOOKUP(tbl_Facturas[[#This Row],[Key_Fact]],tbl_Manifiestos[Key_Manif],tbl_Manifiestos[Pagado a Broker],0),0) -> 0 | T86: 44197.31
A87: 3-2-2025 | B87: =tbl_Facturas[[#This Row],[Factura]] & "|" & tbl_Facturas[[#This Row],[Proyecto OK]] & "|" & TEXT(tbl_Facturas[[#This Row],[Horas o Viaje]],"0.00") & "|" & TEXT(tbl_Facturas[[#This Row],[Costo unitario]],"0.00") -> 2342|Niles IL|8.00|115.50 | C87: 2342 | D87: 198 | E87: POSADA | G87: 198 | H87: 11455 | I87: Millenium | J87: Niles IL | K87: Niles IL | M87: Reliable Pulaski | P87: 8 | Q87: 115.5 | R87: 924 | S87: =IFERROR(_xlfn.XLOOKUP(tbl_Facturas[[#This Row],[Key_Fact]],tbl_Manifiestos[Key_Manif],tbl_Manifiestos[Pagado a Broker],0),0) -> 859.32 | T87: 45121.31
A88: 3-2-2025 | B88: =tbl_Facturas[[#This Row],[Factura]] & "|" & tbl_Facturas[[#This Row],[Proyecto OK]] & "|" & TEXT(tbl_Facturas[[#This Row],[Horas o Viaje]],"0.00") & "|" & TEXT(tbl_Facturas[[#This Row],[Costo unitario]],"0.00") -> 2342|Niles IL|14.00|115.50 | C88: 2342 | D88: 73 | E88: LI | G88: 73 | H88: 11997 | I88: Millenium | J88: Niles IL | K88: Niles IL | M88: Reliable Pulaski | P88: 14 | Q88: 115.5 | R88: 1617 | S88: =IFERROR(_xlfn.XLOOKUP(tbl_Facturas[[#This Row],[Key_Fact]],tbl_Manifiestos[Key_Manif],tbl_Manifiestos[Pagado a Broker],0),0) -> 0 | T88: 46738.31
A89: 3-2-2025 | B89: =tbl_Facturas[[#This Row],[Factura]] & "|" & tbl_Facturas[[#This Row],[Proyecto OK]] & "|" & TEXT(tbl_Facturas[[#This Row],[Horas o Viaje]],"0.00") & "|" & TEXT(tbl_Facturas[[#This Row],[Costo unitario]],"0.00") -> 2343|Arquilla Park|4.00|110.00 | C89: 2343 | D89: 325 | E89: LT | G89: 325 | H89: 11386 | I89: PanOceanic | K89: Arquilla Park | P89: 4 | Q89: 110 | R89: 440 | S89: =IFERROR(_xlfn.XLOOKUP(tbl_Facturas[[#This Row],[Key_Fact]],tbl_Manifiestos[Key_Manif],tbl_Manifiestos[Pagado a Broker],0),0) -> 409.2 | T89: 47178.31
A90: 3-2-2025 | B90: =tbl_Facturas[[#This Row],[Factura]] & "|" & tbl_Facturas[[#This Row],[Proyecto OK]] & "|" & TEXT(tbl_Facturas[[#This Row],[Horas o Viaje]],"0.00") & "|" & TEXT(tbl_Facturas[[#This Row],[Costo unitario]],"0.00") -> 2344|Lead Replacement Service|10.00|110.00 | C90: 2344 | D90: 617 | E90: LT | G90: 617 | H90: 10569 | I90: PanOceanic | J90: 3347 | K90: Lead Replacement Service | L90: 3347 | P90: 10 | Q90: 110 | R90: 1100 | S90: =IFERROR(_xlfn.XLOOKUP(tbl_Facturas[[#This Row],[Key_Fact]],tbl_Manifiestos[Key_Manif],tbl_Manifiestos[Pagado a Broker],0),0) -> 1023 | T90: 48278.31
A91: 3-2-2025 | B91: =tbl_Facturas[[#This Row],[Factura]] & "|" & tbl_Facturas[[#This Row],[Proyecto OK]] & "|" & TEXT(tbl_Facturas[[#This Row],[Horas o Viaje]],"0.00") & "|" & TEXT(tbl_Facturas[[#This Row],[Costo unitario]],"0.00") -> 2344|Lead Replacement Service|8.50|110.00 | C91: 2344 | D91: 67 | E91: LT | G91: 67 | H91: 11626 | I91: PanOceanic | J91: 3347 | K91: Lead Replacement Service | L91: 3347 | P91: 8.5 | Q91: 110 | R91: 935 | S91: =IFERROR(_xlfn.XLOOKUP(tbl_Facturas[[#This Row],[Key_Fact]],tbl_Manifiestos[Key_Manif],tbl_Manifiestos[Pagado a Broker],0),0) -> 869.55 | T91: 49213.31
A92: 3-2-2025 | B92: =tbl_Facturas[[#This Row],[Factura]] & "|" & tbl_Facturas[[#This Row],[Proyecto OK]] & "|" & TEXT(tbl_Facturas[[#This Row],[Horas o Viaje]],"0.00") & "|" & TEXT(tbl_Facturas[[#This Row],[Costo unitario]],"0.00") -> 2344|Lead Replacement Service|8.00|110.00 | C92: 2344 | D92: 617 | E92: LT | G92: 617 | H92: 10570 | I92: PanOceanic | J92: 3347 | K92: Lead Replacement Service | L92: 3347 | P92: 8 | Q92: 110 | R92: 880 | S92: =IFERROR(_xlfn.XLOOKUP(tbl_Facturas[[#This Row],[Key_Fact]],tbl_Manifiestos[Key_Manif],tbl_Manifiestos[Pagado a Broker],0),0) -> 818.4 | T92: 50093.31
A93: 3-2-2025 | B93: =tbl_Facturas[[#This Row],[Factura]] & "|" & tbl_Facturas[[#This Row],[Proyecto OK]] & "|" & TEXT(tbl_Facturas[[#This Row],[Horas o Viaje]],"0.00") & "|" & TEXT(tbl_Facturas[[#This Row],[Costo unitario]],"0.00") -> 2344|Lead Replacement Service|9.50|110.00 | C93: 2344 | D93: 515 | E93: LT | G93: 515 | H93: 11739 | I93: PanOceanic | J93: 3347 | K93: Lead Replacement Service | L93: 3347 | P93: 9.5 | Q93: 110 | R93: 1045 | S93: =IFERROR(_xlfn.XLOOKUP(tbl_Facturas[[#This Row],[Key_Fact]],tbl_Manifiestos[Key_Manif],tbl_Manifiestos[Pagado a Broker],0),0) -> 971.85 | T93: 51138.31
A94: 3-2-2025 | B94: =tbl_Facturas[[#This Row],[Factura]] & "|" & tbl_Facturas[[#This Row],[Proyecto OK]] & "|" & TEXT(tbl_Facturas[[#This Row],[Horas o Viaje]],"0.00") & "|" & TEXT(tbl_Facturas[[#This Row],[Costo unitario]],"0.00") -> 2344|Lead Replacement Service|9.50|110.00 | C94: 2344 | D94: 617 | E94: LT | G94: 617 | H94: 10571 | I94: PanOceanic | J94: 3347 | K94: Lead Replacement Service | L94: 3347 | P94: 9.5 | Q94: 110 | R94: 1045 | S94: =IFERROR(_xlfn.XLOOKUP(tbl_Facturas[[#This Row],[Key_Fact]],tbl_Manifiestos[Key_Manif],tbl_Manifiestos[Pagado a Broker],0),0) -> 971.85 | T94: 52183.31
A95: 10-2-2025 | B95: =tbl_Facturas[[#This Row],[Factura]] & "|" & tbl_Facturas[[#This Row],[Proyecto OK]] & "|" & TEXT(tbl_Facturas[[#This Row],[Horas o Viaje]],"0.00") & "|" & TEXT(tbl_Facturas[[#This Row],[Costo unitario]],"0.00") -> 2345|Lead Service Replacement|9.50|120.00 | C95: 2345 | D95: 515 | E95: LT | G95: 515 | H95: 11744 | I95: Benchmark | J95: 2332-01Lead Service Replacement | K95: Lead Service Replacement | L95: 2332-01 | P95: 9.5 | Q95: 120 | R95: 1140 | S95: =IFERROR(_xlfn.XLOOKUP(tbl_Facturas[[#This Row],[Key_Fact]],tbl_Manifiestos[Key_Manif],tbl_Manifiestos[Pagado a Broker],0),0) -> 1060.2 | T95: 53323.31
A96: 10-2-2025 | B96: =tbl_Facturas[[#This Row],[Factura]] & "|" & tbl_Facturas[[#This Row],[Proyecto OK]] & "|" & TEXT(tbl_Facturas[[#This Row],[Horas o Viaje]],"0.00") & "|" & TEXT(tbl_Facturas[[#This Row],[Costo unitario]],"0.00") -> 2345|Lead Service Replacement|9.00|120.00 | C96: 2345 | D96: 308 | E96: AAA | G96: 308 | H96: 11106 | I96: Benchmark | J96: 2332-01Lead Service Replacement | K96: Lead Service Replacement | L96: 2332-01 | P96: 9 | Q96: 120 | R96: 1080 | S96: =IFERROR(_xlfn.XLOOKUP(tbl_Facturas[[#This Row],[Key_Fact]],tbl_Manifiestos[Key_Manif],tbl_Manifiestos[Pagado a Broker],0),0) -> 1004.4 | T96: 54403.31
A97: 10-2-2025 | B97: =tbl_Facturas[[#This Row],[Factura]] & "|" & tbl_Facturas[[#This Row],[Proyecto OK]] & "|" & TEXT(tbl_Facturas[[#This Row],[Horas o Viaje]],"0.00") & "|" & TEXT(tbl_Facturas[[#This Row],[Costo unitario]],"0.00") -> 2345|Lead Service Replacement|9.00|120.00 | C97: 2345 | D97: 67 | E97: LT | G97: 67 | H97: 11628 | I97: Benchmark | J97: 2332-01Lead Service Replacement | K97: Lead Service Replacement | L97: 2332-01 | P97: 9 | Q97: 120 | R97: 1080 | S97: =IFERROR(_xlfn.XLOOKUP(tbl_Facturas[[#This Row],[Key_Fact]],tbl_Manifiestos[Key_Manif],tbl_Manifiestos[Pagado a Broker],0),0) -> 1004.4 | T97: 55483.31
A98: 10-2-2025 | B98: =tbl_Facturas[[#This Row],[Factura]] & "|" & tbl_Facturas[[#This Row],[Proyecto OK]] & "|" & TEXT(tbl_Facturas[[#This Row],[Horas o Viaje]],"0.00") & "|" & TEXT(tbl_Facturas[[#This Row],[Costo unitario]],"0.00") -> 2345|Lead Service Replacement|9.00|120.00 | C98: 2345 | D98: 11 | E98: MLB | G98: 11 | H98: 10811 | I98: Benchmark | J98: 2332-01Lead Service Replacement | K98: Lead Service Replacement | L98: 2332-01 | P98: 9 | Q98: 120 | R98: 1080 | S98: =IFERROR(_xlfn.XLOOKUP(tbl_Facturas[[#This Row],[Key_Fact]],tbl_Manifiestos[Key_Manif],tbl_Manifiestos[Pagado a Broker],0),0) -> 1004.4 | T98: 56563.31
A99: 10-2-2025 | B99: =tbl_Facturas[[#This Row],[Factura]] & "|" & tbl_Facturas[[#This Row],[Proyecto OK]] & "|" & TEXT(tbl_Facturas[[#This Row],[Horas o Viaje]],"0.00") & "|" & TEXT(tbl_Facturas[[#This Row],[Costo unitario]],"0.00") -> 2345|Lead Service Replacement|9.00|120.00 | C99: 2345 | D99: 73 | E99: LI | G99: 73 | H99: 11999 | I99: Benchmark | J99: 2332-01Lead Service Replacement | K99: Lead Service Replacement | L99: 2332-01 | P99: 9 | Q99: 120 | R99: 1080 | S99: =IFERROR(_xlfn.XLOOKUP(tbl_Facturas[[#This Row],[Key_Fact]],tbl_Manifiestos[Key_Manif],tbl_Manifiestos[Pagado a Broker],0),0) -> 1004.4 | T99: 57643.31
A100: 10-2-2025 | B100: =tbl_Facturas[[#This Row],[Factura]] & "|" & tbl_Facturas[[#This Row],[Proyecto OK]] & "|" & TEXT(tbl_Facturas[[#This Row],[Horas o Viaje]],"0.00") & "|" & TEXT(tbl_Facturas[[#This Row],[Costo unitario]],"0.00") -> 2346|Canal #2 |1.25|132.30 | C100: 2346 | D100: 19 | F100: MLB | G100: 19 | H100: 10734 | I100: FHP | J100: Canal #2Job# 6227 | K100: Canal #2 | L100: 6227 | M100: Vulcan Pershing | O100: WAITING TIME | P100: 1.25 | Q100: 132.3 | R100: 165.38 | S100: =IFERROR(_xlfn.XLOOKUP(tbl_Facturas[[#This Row],[Key_Fact]],tbl_Manifiestos[Key_Manif],tbl_Manifiestos[Pagado a Broker],0),0) -> 0 | T100: 57808.69
...

Sheet Manifiestos Varios
A1: Proveedor | B1: Key_Manif | C1: Factura | D1: Fecha | E1: Brocker | F1: Customer | G1: Proyecto | H1: Proyecto OK | I1: Job Ok | J1: Servicio | K1: Costo Unitario | L1: Total Pagado | M1: Pagado a Broker | N1: Porcentaje
A2: J&O | B2: =tbl_Manifiestos[[#This Row],[Factura]] & "|" & tbl_Manifiestos[[#This Row],[Proyecto OK]] & "|" & TEXT(tbl_Manifiestos[[#This Row],[Servicio]],"0.00") & "|" & TEXT(tbl_Manifiestos[[#This Row],[Costo Unitario]],"0.00") -> 2768|Metra 115th|5.00|220.00 | C2: 2768 | D2: 45925 | E2: 686 | F2: Viridian | G2: 41 | H2: Metra 115th | J2: 5 | K2: 220 | L2: 1100 | M2: =tbl_Manifiestos[[#This Row],[Total Pagado]]*tbl_Manifiestos[[#This Row],[Porcentaje]] -> 990 | N2: 0.9
A3: MJV | B3: =tbl_Manifiestos[[#This Row],[Factura]] & "|" & tbl_Manifiestos[[#This Row],[Proyecto OK]] & "|" & TEXT(tbl_Manifiestos[[#This Row],[Servicio]],"0.00") & "|" & TEXT(tbl_Manifiestos[[#This Row],[Costo Unitario]],"0.00") -> 2441|F.M.|8.00|100.00 | C3: 2441 | D3: 45778 | E3: MJV-678 | F3: Foundation Mechanics | G3: 52.34 | H3: F.M. | J3: 8 | K3: 100 | L3: 800 | M3: =tbl_Manifiestos[[#This Row],[Total Pagado]]*tbl_Manifiestos[[#This Row],[Porcentaje]] -> 720 | N3: 0.9
A4: XPREZ | B4: =tbl_Manifiestos[[#This Row],[Factura]] & "|" & tbl_Manifiestos[[#This Row],[Proyecto OK]] & "|" & TEXT(tbl_Manifiestos[[#This Row],[Servicio]],"0.00") & "|" & TEXT(tbl_Manifiestos[[#This Row],[Costo Unitario]],"0.00") -> 2441|F.M.|8.00|100.00 | C4: 2441 | D4: 45778 | E4: XPRES-4 | F4: Foundation Mechanics | G4: 55.75 | H4: F.M. | J4: 8 | K4: 100 | L4: 800 | M4: =tbl_Manifiestos[[#This Row],[Total Pagado]]*tbl_Manifiestos[[#This Row],[Porcentaje]] -> 720 | N4: 0.9
A5: MJV | B5: =tbl_Manifiestos[[#This Row],[Factura]] & "|" & tbl_Manifiestos[[#This Row],[Proyecto OK]] & "|" & TEXT(tbl_Manifiestos[[#This Row],[Servicio]],"0.00") & "|" & TEXT(tbl_Manifiestos[[#This Row],[Costo Unitario]],"0.00") -> 2441|F.M.|8.00|100.00 | C5: 2441 | D5: 45770 | E5: MJV-678 | F5: Foundation Mechanics | G5: 73.78 | H5: F.M. | J5: 8 | K5: 100 | L5: 800 | M5: =tbl_Manifiestos[[#This Row],[Total Pagado]]*tbl_Manifiestos[[#This Row],[Porcentaje]] -> 720 | N5: 0.9
A6: XPREZ | B6: =tbl_Manifiestos[[#This Row],[Factura]] & "|" & tbl_Manifiestos[[#This Row],[Proyecto OK]] & "|" & TEXT(tbl_Manifiestos[[#This Row],[Servicio]],"0.00") & "|" & TEXT(tbl_Manifiestos[[#This Row],[Costo Unitario]],"0.00") -> 2441|F.M.|8.00|100.00 | C6: 2441 | D6: 45770 | E6: XPRES-4 | F6: Foundation Mechanics | G6: 82.91 | H6: F.M. | J6: 8 | K6: 100 | L6: 800 | M6: =tbl_Manifiestos[[#This Row],[Total Pagado]]*tbl_Manifiestos[[#This Row],[Porcentaje]] -> 720 | N6: 0.9
A7: CAJETAS | B7: =tbl_Manifiestos[[#This Row],[Factura]] & "|" & tbl_Manifiestos[[#This Row],[Proyecto OK]] & "|" & TEXT(tbl_Manifiestos[[#This Row],[Servicio]],"0.00") & "|" & TEXT(tbl_Manifiestos[[#This Row],[Costo Unitario]],"0.00") -> 2641|CDOT S-403|8.50|105.00 | C7: 2641 | D7: 45870 | E7: 54 | F7: Sumit | G7: 403 | H7: CDOT S-403 | J7: 8.5 | K7: 105 | L7: 892.5 | M7: =tbl_Manifiestos[[#This Row],[Total Pagado]]*tbl_Manifiestos[[#This Row],[Porcentaje]] -> 803.25 | N7: 0.9
A8: BBR | B8: =tbl_Manifiestos[[#This Row],[Factura]] & "|" & tbl_Manifiestos[[#This Row],[Proyecto OK]] & "|" & TEXT(tbl_Manifiestos[[#This Row],[Servicio]],"0.00") & "|" & TEXT(tbl_Manifiestos[[#This Row],[Costo Unitario]],"0.00") -> 2656|CDOT S-403|10.50|105.00 | C8: 2656 | D8: 45874 | E8: 25 | F8: Sumit | G8: 403 | H8: CDOT S-403 | J8: 10.5 | K8: 105 | L8: 1102.5 | M8: =tbl_Manifiestos[[#This Row],[Total Pagado]]*tbl_Manifiestos[[#This Row],[Porcentaje]] -> 992.25 | N8: 0.9
A9: BBR | B9: =tbl_Manifiestos[[#This Row],[Factura]] & "|" & tbl_Manifiestos[[#This Row],[Proyecto OK]] & "|" & TEXT(tbl_Manifiestos[[#This Row],[Servicio]],"0.00") & "|" & TEXT(tbl_Manifiestos[[#This Row],[Costo Unitario]],"0.00") -> 2669|CDOT S-403|9.00|105.00 | C9: 2669 | D9: 45875 | E9: 25 | F9: Sumit | G9: 403 | H9: CDOT S-403 | J9: 9 | K9: 105 | L9: 945 | M9: =tbl_Manifiestos[[#This Row],[Total Pagado]]*tbl_Manifiestos[[#This Row],[Porcentaje]] -> 850.5 | N9: 0.9
A10: BBR | B10: =tbl_Manifiestos[[#This Row],[Factura]] & "|" & tbl_Manifiestos[[#This Row],[Proyecto OK]] & "|" & TEXT(tbl_Manifiestos[[#This Row],[Servicio]],"0.00") & "|" & TEXT(tbl_Manifiestos[[#This Row],[Costo Unitario]],"0.00") -> 2669|CDOT S-403|9.00|105.00 | C10: 2669 | D10: 45876 | E10: 25 | F10: Sumit | G10: 403 | H10: CDOT S-403 | J10: 9 | K10: 105 | L10: 945 | M10: =tbl_Manifiestos[[#This Row],[Total Pagado]]*tbl_Manifiestos[[#This Row],[Porcentaje]] -> 850.5 | N10: 0.9
A11: HERRERA | B11: =tbl_Manifiestos[[#This Row],[Factura]] & "|" & tbl_Manifiestos[[#This Row],[Proyecto OK]] & "|" & TEXT(tbl_Manifiestos[[#This Row],[Servicio]],"0.00") & "|" & TEXT(tbl_Manifiestos[[#This Row],[Costo Unitario]],"0.00") -> 2669|CDOT S-403|8.50|105.00 | C11: 2669 | D11: 45884 | E11: 92 | F11: Sumit | G11: 403 | H11: CDOT S-403 | J11: 8.5 | K11: 105 | L11: 892.5 | M11: =tbl_Manifiestos[[#This Row],[Total Pagado]]*tbl_Manifiestos[[#This Row],[Porcentaje]] -> 803.25 | N11: 0.9
A12: UMBRELLA | B12: =tbl_Manifiestos[[#This Row],[Factura]] & "|" & tbl_Manifiestos[[#This Row],[Proyecto OK]] & "|" & TEXT(tbl_Manifiestos[[#This Row],[Servicio]],"0.00") & "|" & TEXT(tbl_Manifiestos[[#This Row],[Costo Unitario]],"0.00") -> 2656|CDOT S-403|8.00|105.00 | C12: 2656 | D12: 45873 | E12: 661 | F12: Sumit | G12: 403 | H12: CDOT S-403 | J12: 8 | K12: 105 | L12: 840 | M12: =tbl_Manifiestos[[#This Row],[Total Pagado]]*tbl_Manifiestos[[#This Row],[Porcentaje]] -> 756 | N12: 0.9
A13: UMBRELLA | B13: =tbl_Manifiestos[[#This Row],[Factura]] & "|" & tbl_Manifiestos[[#This Row],[Proyecto OK]] & "|" & TEXT(tbl_Manifiestos[[#This Row],[Servicio]],"0.00") & "|" & TEXT(tbl_Manifiestos[[#This Row],[Costo Unitario]],"0.00") -> 2656|CDOT S-403|9.50|105.00 | C13: 2656 | D13: 45874 | E13: 661 | F13: Sumit | G13: 403 | H13: CDOT S-403 | J13: 9.5 | K13: 105 | L13: 997.5 | M13: =tbl_Manifiestos[[#This Row],[Total Pagado]]*tbl_Manifiestos[[#This Row],[Porcentaje]] -> 897.75 | N13: 0.9
A14: UMBRELLA | B14: =tbl_Manifiestos[[#This Row],[Factura]] & "|" & tbl_Manifiestos[[#This Row],[Proyecto OK]] & "|" & TEXT(tbl_Manifiestos[[#This Row],[Servicio]],"0.00") & "|" & TEXT(tbl_Manifiestos[[#This Row],[Costo Unitario]],"0.00") -> 2656|CDOT S-403|9.00|105.00 | C14: 2656 | D14: 45875 | E14: 661 | F14: Sumit | G14: 403 | H14: CDOT S-403 | J14: 9 | K14: 105 | L14: 945 | M14: =tbl_Manifiestos[[#This Row],[Total Pagado]]*tbl_Manifiestos[[#This Row],[Porcentaje]] -> 850.5 | N14: 0.9
A15: UMBRELLA | B15: =tbl_Manifiestos[[#This Row],[Factura]] & "|" & tbl_Manifiestos[[#This Row],[Proyecto OK]] & "|" & TEXT(tbl_Manifiestos[[#This Row],[Servicio]],"0.00") & "|" & TEXT(tbl_Manifiestos[[#This Row],[Costo Unitario]],"0.00") -> 2669|CDOT S-403|8.00|105.00 | C15: 2669 | D15: 45881 | E15: 28 | F15: Sumit | G15: 403 | H15: CDOT S-403 | J15: 8 | K15: 105 | L15: 840 | M15: =tbl_Manifiestos[[#This Row],[Total Pagado]]*tbl_Manifiestos[[#This Row],[Porcentaje]] -> 756 | N15: 0.9
A16: UMBRELLA | B16: =tbl_Manifiestos[[#This Row],[Factura]] & "|" & tbl_Manifiestos[[#This Row],[Proyecto OK]] & "|" & TEXT(tbl_Manifiestos[[#This Row],[Servicio]],"0.00") & "|" & TEXT(tbl_Manifiestos[[#This Row],[Costo Unitario]],"0.00") -> 2669|CDOT S-403|8.00|105.00 | C16: 2669 | D16: 45882 | E16: 28 | F16: Sumit | G16: 403 | H16: CDOT S-403 | J16: 8 | K16: 105 | L16: 840 | M16: =tbl_Manifiestos[[#This Row],[Total Pagado]]*tbl_Manifiestos[[#This Row],[Porcentaje]] -> 756 | N16: 0.9
A17: WO | B17: =tbl_Manifiestos[[#This Row],[Factura]] & "|" & tbl_Manifiestos[[#This Row],[Proyecto OK]] & "|" & TEXT(tbl_Manifiestos[[#This Row],[Servicio]],"0.00") & "|" & TEXT(tbl_Manifiestos[[#This Row],[Costo Unitario]],"0.00") -> 2682|CDOT S-403|9.00|105.00 | C17: 2682 | D17: 45891 | E17: 102 | F17: Sumit | G17: 403 | H17: CDOT S-403 | J17: 9 | K17: 105 | L17: 945 | M17: =tbl_Manifiestos[[#This Row],[Total Pagado]]*tbl_Manifiestos[[#This Row],[Porcentaje]] -> 850.5 | N17: 0.9
A18: CAJETAS | B18: =tbl_Manifiestos[[#This Row],[Factura]] & "|" & tbl_Manifiestos[[#This Row],[Proyecto OK]] & "|" & TEXT(tbl_Manifiestos[[#This Row],[Servicio]],"0.00") & "|" & TEXT(tbl_Manifiestos[[#This Row],[Costo Unitario]],"0.00") -> 2698|CDOT S-403|9.00|105.00 | C18: 2698 | D18: 45896 | E18: 606 | F18: Sumit | G18: 403 | H18: CDOT S-403 | J18: 9 | K18: 105 | L18: 945 | M18: =tbl_Manifiestos[[#This Row],[Total Pagado]]*tbl_Manifiestos[[#This Row],[Porcentaje]] -> 850.5 | N18: 0.9
... A38: WO | B38: =tbl_Manifiestos[[#This Row],[Factura]] & "|" & tbl_Manifiestos[[#This Row],[Proyecto OK]] & "|" & TEXT(tbl_Manifiestos[[#This Row],[Servicio]],"0.00") & "|" & TEXT(tbl_Manifiestos[[#This Row],[Costo Unitario]],"0.00") -> 2910|CDOT S-403|8.00|105.00 | C38: 2910 | D38: 45978 | E38: 7 | F38: Sumit | G38: 403 | H38: CDOT S-403 | J38: 8 | K38: 105 | L38: 840 | M38: =tbl_Manifiestos[[#This Row],[Total Pagado]]*tbl_Manifiestos[[#This Row],[Porcentaje]] -> 756 | N38: 0.9
A39: LT | B39: =tbl_Manifiestos[[#This Row],[Factura]] & "|" & tbl_Manifiestos[[#This Row],[Proyecto OK]] & "|" & TEXT(tbl_Manifiestos[[#This Row],[Servicio]],"0.00") & "|" & TEXT(tbl_Manifiestos[[#This Row],[Costo Unitario]],"0.00") -> 2641|CDOT S-403|9.50|115.00 | C39: 2641 | D39: 45868 | E39: 325 | F39: Sumit | G39: 403 | H39: CDOT S-403 | J39: 9.5 | K39: 115 | L39: =J39*K39 -> 1092.5 | M39: =tbl_Manifiestos[[#This Row],[Total Pagado]]*tbl_Manifiestos[[#This Row],[Porcentaje]] -> 1016.025 | N39: 0.93
A40: LT | B40: =tbl_Manifiestos[[#This Row],[Factura]] & "|" & tbl_Manifiestos[[#This Row],[Proyecto OK]] & "|" & TEXT(tbl_Manifiestos[[#This Row],[Servicio]],"0.00") & "|" & TEXT(tbl_Manifiestos[[#This Row],[Costo Unitario]],"0.00") -> 2641|CDOT S-403|10.00|115.00 | C40: 2641 | D40: 45869 | E40: 325 | F40: Sumit | G40: 403 | H40: CDOT S-403 | J40: 10 | K40: 115 | L40: =J40*K40 -> 1150 | M40: =tbl_Manifiestos[[#This Row],[Total Pagado]]*tbl_Manifiestos[[#This Row],[Porcentaje]] -> 1069.5 | N40: 0.93
A41: LT | B41: =tbl_Manifiestos[[#This Row],[Factura]] & "|" & tbl_Manifiestos[[#This Row],[Proyecto OK]] & "|" & TEXT(tbl_Manifiestos[[#This Row],[Servicio]],"0.00") & "|" & TEXT(tbl_Manifiestos[[#This Row],[Costo Unitario]],"0.00") -> 2641|CDOT S-403|8.50|115.00 | C41: 2641 | D41: 45870 | E41: 325 | F41: Sumit | G41: 403 | H41: CDOT S-403 | J41: 8.5 | K41: 115 | L41: =J41*K41 -> 977.5 | M41: =tbl_Manifiestos[[#This Row],[Total Pagado]]*tbl_Manifiestos[[#This Row],[Porcentaje]] -> 909.075 | N41: 0.93
A42: LT | B42: =tbl_Manifiestos[[#This Row],[Factura]] & "|" & tbl_Manifiestos[[#This Row],[Proyecto OK]] & "|" & TEXT(tbl_Manifiestos[[#This Row],[Servicio]],"0.00") & "|" & TEXT(tbl_Manifiestos[[#This Row],[Costo Unitario]],"0.00") -> 2656|CDOT S-403|9.00|115.00 | C42: 2656 | D42: 45873 | E42: 325 | F42: Sumit | G42: 403 | H42: CDOT S-403 | J42: 9 | K42: 115 | L42: =J42*K42 -> 1035 | M42: =tbl_Manifiestos[[#This Row],[Total Pagado]]*tbl_Manifiestos[[#This Row],[Porcentaje]] -> 962.55 | N42: 0.93
A43: LT | B43: =tbl_Manifiestos[[#This Row],[Factura]] & "|" & tbl_Manifiestos[[#This Row],[Proyecto OK]] & "|" & TEXT(tbl_Manifiestos[[#This Row],[Servicio]],"0.00") & "|" & TEXT(tbl_Manifiestos[[#This Row],[Costo Unitario]],"0.00") -> 2656|CDOT S-403|10.50|115.00 | C43: 2656 | D43: 45875 | E43: 325 | F43: Sumit | G43: 403 | H43: CDOT S-403 | J43: 10.5 | K43: 115 | L43: =J43*K43 -> 1207.5 | M43: =tbl_Manifiestos[[#This Row],[Total Pagado]]*tbl_Manifiestos[[#This Row],[Porcentaje]] -> 1122.975 | N43: 0.93
A44: LT | B44: =tbl_Manifiestos[[#This Row],[Factura]] & "|" & tbl_Manifiestos[[#This Row],[Proyecto OK]] & "|" & TEXT(tbl_Manifiestos[[#This Row],[Servicio]],"0.00") & "|" & TEXT(tbl_Manifiestos[[#This Row],[Costo Unitario]],"0.00") -> 2656|CDOT S-403|9.25|115.00 | C44: 2656 | D44: 45877 | E44: 325 | F44: Sumit | G44: 403 | H44: CDOT S-403 | J44: 9.25 | K44: 115 | L44: =J44*K44 -> 1063.75 | M44: =tbl_Manifiestos[[#This Row],[Total Pagado]]*tbl_Manifiestos[[#This Row],[Porcentaje]] -> 989.2875 | N44: 0.93
A45: LT | B45: =tbl_Manifiestos[[#This Row],[Factura]] & "|" & tbl_Manifiestos[[#This Row],[Proyecto OK]] & "|" & TEXT(tbl_Manifiestos[[#This Row],[Servicio]],"0.00") & "|" & TEXT(tbl_Manifiestos[[#This Row],[Costo Unitario]],"0.00") -> 2656|CDOT S-403|10.50|115.00 | C45: 2656 | D45: 45876 | E45: 325 | F45: Sumit | G45: 403 | H45: CDOT S-403 | J45: 10.5 | K45: 115 | L45: =J45*K45 -> 1207.5 | M45: =tbl_Manifiestos[[#This Row],[Total Pagado]]*tbl_Manifiestos[[#This Row],[Porcentaje]] -> 1122.975 | N45: 0.93
A46: LT | B46: =tbl_Manifiestos[[#This Row],[Factura]] & "|" & tbl_Manifiestos[[#This Row],[Proyecto OK]] & "|" & TEXT(tbl_Manifiestos[[#This Row],[Servicio]],"0.00") & "|" & TEXT(tbl_Manifiestos[[#This Row],[Costo Unitario]],"0.00") -> 2656|CDOT S-403|9.50|115.00 | C46: 2656 | D46: 45874 | E46: 325 | F46: Sumit | G46: 403 | H46: CDOT S-403 | J46: 9.5 | K46: 115 | L46: =J46*K46 -> 1092.5 | M46: =tbl_Manifiestos[[#This Row],[Total Pagado]]*tbl_Manifiestos[[#This Row],[Porcentaje]] -> 1016.025 | N46: 0.93
A47: LT | B47: =tbl_Manifiestos[[#This Row],[Factura]] & "|" & tbl_Manifiestos[[#This Row],[Proyecto OK]] & "|" & TEXT(tbl_Manifiestos[[#This Row],[Servicio]],"0.00") & "|" & TEXT(tbl_Manifiestos[[#This Row],[Costo Unitario]],"0.00") -> 2669|CDOT S-403|10.00|115.00 | C47: 2669 | D47: 45880 | E47: 325 | F47: Sumit | G47: 403 | H47: CDOT S-403 | J47: 10 | K47: 115 | L47: =J47*K47 -> 1150 | M47: =tbl_Manifiestos[[#This Row],[Total Pagado]]*tbl_Manifiestos[[#This Row],[Porcentaje]] -> 1069.5 | N47: 0.93
A48: LT | B48: =tbl_Manifiestos[[#This Row],[Factura]] & "|" & tbl_Manifiestos[[#This Row],[Proyecto OK]] & "|" & TEXT(tbl_Manifiestos[[#This Row],[Servicio]],"0.00") & "|" & TEXT(tbl_Manifiestos[[#This Row],[Costo Unitario]],"0.00") -> 2669|CDOT S-403|8.00|115.00 | C48: 2669 | D48: 45881 | E48: 325 | F48: Sumit | G48: 403 | H48: CDOT S-403 | J48: 8 | K48: 115 | L48: =J48*K48 -> 920 | M48: =tbl_Manifiestos[[#This Row],[Total Pagado]]*tbl_Manifiestos[[#This Row],[Porcentaje]] -> 855.6 | N48: 0.93
A49: LT | B49: =tbl_Manifiestos[[#This Row],[Factura]] & "|" & tbl_Manifiestos[[#This Row],[Proyecto OK]] & "|" & TEXT(tbl_Manifiestos[[#This Row],[Servicio]],"0.00") & "|" & TEXT(tbl_Manifiestos[[#This Row],[Costo Unitario]],"0.00") -> 2669|CDOT S-403|10.00|115.00 | C49: 2669 | D49: 45882 | E49: 325 | F49: Sumit | G49: 403 | H49: CDOT S-403 | J49: 10 | K49: 115 | L49: =J49*K49 -> 1150 | M49: =tbl_Manifiestos[[#This Row],[Total Pagado]]*tbl_Manifiestos[[#This Row],[Porcentaje]] -> 1069.5 | N49: 0.93
A50: LT | B50: =tbl_Manifiestos[[#This Row],[Factura]] & "|" & tbl_Manifiestos[[#This Row],[Proyecto OK]] & "|" & TEXT(tbl_Manifiestos[[#This Row],[Servicio]],"0.00") & "|" & TEXT(tbl_Manifiestos[[#This Row],[Costo Unitario]],"0.00") -> 2669|CDOT S-403|9.00|115.00 | C50: 2669 | D50: 45883 | E50: 325 | F50: Sumit | G50: 403 | H50: CDOT S-403 | J50: 9 | K50: 115 | L50: =J50*K50 -> 1035 | M50: =tbl_Manifiestos[[#This Row],[Total Pagado]]*tbl_Manifiestos[[#This Row],[Porcentaje]] -> 962.55 | N50: 0.93
... A105: MLB | B105: =tbl_Manifiestos[[#This Row],[Factura]] & "|" & tbl_Manifiestos[[#This Row],[Proyecto OK]] & "|" & TEXT(tbl_Manifiestos[[#This Row],[Servicio]],"0.00") & "|" & TEXT(tbl_Manifiestos[[#This Row],[Costo Unitario]],"0.00") -> 2781|CDOT S-403|9.00|115.00 | C105: 2781 | D105: 45931 | E105: 82 | F105: Sumit | G105: 403 | H105: CDOT S-403 | J105: 9 | K105: 115 | L105: =J105*K105 -> 1035 | M105: =tbl_Manifiestos[[#This Row],[Total Pagado]]*tbl_Manifiestos[[#This Row],[Porcentaje]] -> 962.55 | N105: 0.93
A106: MLB | B106: =tbl_Manifiestos[[#This Row],[Factura]] & "|" & tbl_Manifiestos[[#This Row],[Proyecto OK]] & "|" & TEXT(tbl_Manifiestos[[#This Row],[Servicio]],"0.00") & "|" & TEXT(tbl_Manifiestos[[#This Row],[Costo Unitario]],"0.00") -> 2796|CDOT S-403|9.00|115.00 | C106: 2796 | D106: 45936 | E106: 11 | F106: Sumit | G106: 403 | H106: CDOT S-403 | J106: 9 | K106: 115 | L106: 1035 | M106: =tbl_Manifiestos[[#This Row],[Total Pagado]]*tbl_Manifiestos[[#This Row],[Porcentaje]] -> 962.55 | N106: 0.93
A107: MLB | B107: =tbl_Manifiestos[[#This Row],[Factura]] & "|" & tbl_Manifiestos[[#This Row],[Proyecto OK]] & "|" & TEXT(tbl_Manifiestos[[#This Row],[Servicio]],"0.00") & "|" & TEXT(tbl_Manifiestos[[#This Row],[Costo Unitario]],"0.00") -> 2796|CDOT S-403|8.00|115.00 | C107: 2796 | D107: 45938 | E107: 82 | F107: Sumit | G107: 403 | H107: CDOT S-403 | J107: 8 | K107: 115 | L107: 920 | M107: =tbl_Manifiestos[[#This Row],[Total Pagado]]*tbl_Manifiestos[[#This Row],[Porcentaje]] -> 855.6 | N107: 0.93
A108: MLB | B108: =tbl_Manifiestos[[#This Row],[Factura]] & "|" & tbl_Manifiestos[[#This Row],[Proyecto OK]] & "|" & TEXT(tbl_Manifiestos[[#This Row],[Servicio]],"0.00") & "|" & TEXT(tbl_Manifiestos[[#This Row],[Costo Unitario]],"0.00") -> 2796|CDOT S-403|8.00|115.00 | C108: 2796 | D108: 45939 | E108: 82 | F108: Sumit | G108: 403 | H108: CDOT S-403 | J108: 8 | K108: 115 | L108: 920 | M108: =tbl_Manifiestos[[#This Row],[Total Pagado]]*tbl_Manifiestos[[#This Row],[Porcentaje]] -> 855.6 | N108: 0.93
A109: MLB | B109: =tbl_Manifiestos[[#This Row],[Factura]] & "|" & tbl_Manifiestos[[#This Row],[Proyecto OK]] & "|" & TEXT(tbl_Manifiestos[[#This Row],[Servicio]],"0.00") & "|" & TEXT(tbl_Manifiestos[[#This Row],[Costo Unitario]],"0.00") -> 2796|CDOT S-403|8.00|115.00 | C109: 2796 | D109: 45940 | E109: 82 | F109: Sumit | G109: 403 | H109: CDOT S-403 | J109: 8 | K109: 115 | L109: 920 | M109: =tbl_Manifiestos[[#This Row],[Total Pagado]]*tbl_Manifiestos[[#This Row],[Porcentaje]] -> 855.6 | N109: 0.93
A110: MLB | B110: =tbl_Manifiestos[[#This Row],[Factura]] & "|" & tbl_Manifiestos[[#This Row],[Proyecto OK]] & "|" & TEXT(tbl_Manifiestos[[#This Row],[Servicio]],"0.00") & "|" & TEXT(tbl_Manifiestos[[#This Row],[Costo Unitario]],"0.00") -> 2811|CDOT S-403|8.00|115.00 | C110: 2811 | D110: 45943 | E110: 82 | F110: Sumit | G110: 403 | H110: CDOT S-403 | J110: 8 | K110: 115 | L110: =J110*K110 -> 920 | M110: =tbl_Manifiestos[[#This Row],[Total Pagado]]*tbl_Manifiestos[[#This Row],[Porcentaje]] -> 855.6 | N110: 0.93
A111: MLB | B111: =tbl_Manifiestos[[#This Row],[Factura]] & "|" & tbl_Manifiestos[[#This Row],[Proyecto OK]] & "|" & TEXT(tbl_Manifiestos[[#This Row],[Servicio]],"0.00") & "|" & TEXT(tbl_Manifiestos[[#This Row],[Costo Unitario]],"0.00") -> 2811|CDOT S-403|9.00|115.00 | C111: 2811 | D111: 45944 | E111: 82 | F111: Sumit | G111: 403 | H111: CDOT S-403 | J111: 9 | K111: 115 | L111: =J111*K111 -> 1035 | M111: =tbl_Manifiestos[[#This Row],[Total Pagado]]*tbl_Manifiestos[[#This Row],[Porcentaje]] -> 962.55 | N111: 0.93
A112: MLB | B112: =tbl_Manifiestos[[#This Row],[Factura]] & "|" & tbl_Manifiestos[[#This Row],[Proyecto OK]] & "|" & TEXT(tbl_Manifiestos[[#This Row],[Servicio]],"0.00") & "|" & TEXT(tbl_Manifiestos[[#This Row],[Costo Unitario]],"0.00") -> 2811|CDOT S-403|9.00|115.00 | C112: 2811 | D112: 45945 | E112: 82 | F112: Sumit | G112: 403 | H112: CDOT S-403 | J112: 9 | K112: 115 | L112: =J112*K112 -> 1035 | M112: =tbl_Manifiestos[[#This Row],[Total Pagado]]*tbl_Manifiestos[[#This Row],[Porcentaje]] -> 962.55 | N112: 0.93
A113: MLB | B113: =tbl_Manifiestos[[#This Row],[Factura]] & "|" & tbl_Manifiestos[[#This Row],[Proyecto OK]] & "|" & TEXT(tbl_Manifiestos[[#This Row],[Servicio]],"0.00") & "|" & TEXT(tbl_Manifiestos[[#This Row],[Costo Unitario]],"0.00") -> 2811|CDOT S-403|9.00|115.00 | C113: 2811 | D113: 45946 | E113: 82 | F113: Sumit | G113: 403 | H113: CDOT S-403 | J113: 9 | K113: 115 | L113: =J113*K113 -> 1035 | M113: =tbl_Manifiestos[[#This Row],[Total Pagado]]*tbl_Manifiestos[[#This Row],[Porcentaje]] -> 962.55 | N113: 0.93
A114: MLB | B114: =tbl_Manifiestos[[#This Row],[Factura]] & "|" & tbl_Manifiestos[[#This Row],[Proyecto OK]] & "|" & TEXT(tbl_Manifiestos[[#This Row],[Servicio]],"0.00") & "|" & TEXT(tbl_Manifiestos[[#This Row],[Costo Unitario]],"0.00") -> 2811|CDOT S-403|9.00|115.00 | C114: 2811 | D114: 45947 | E114: 82 | F114: Sumit | G114: 403 | H114: CDOT S-403 | J114: 9 | K114: 115 | L114: =J114*K114 -> 1035 | M114: =tbl_Manifiestos[[#This Row],[Total Pagado]]*tbl_Manifiestos[[#This Row],[Porcentaje]] -> 962.55 | N114: 0.93
A115: MLB | B115: =tbl_Manifiestos[[#This Row],[Factura]] & "|" & tbl_Manifiestos[[#This Row],[Proyecto OK]] & "|" & TEXT(tbl_Manifiestos[[#This Row],[Servicio]],"0.00") & "|" & TEXT(tbl_Manifiestos[[#This Row],[Costo Unitario]],"0.00") -> 2833|CDOT S-403|8.00|115.00 | C115: 2833 | D115: 45950 | E115: 82 | F115: Sumit | G115: 403 | H115: CDOT S-403 | J115: 8 | K115: 115 | L115: =J115*K115 -> 920 | M115: =tbl_Manifiestos[[#This Row],[Total Pagado]]*tbl_Manifiestos[[#This Row],[Porcentaje]] -> 855.6 | N115: 0.93
A116: MLB | B116: =tbl_Manifiestos[[#This Row],[Factura]] & "|" & tbl_Manifiestos[[#This Row],[Proyecto OK]] & "|" & TEXT(tbl_Manifiestos[[#This Row],[Servicio]],"0.00") & "|" & TEXT(tbl_Manifiestos[[#This Row],[Costo Unitario]],"0.00") -> 2833|CDOT S-403|10.00|115.00 | C116: 2833 | D116: 45951 | E116: 82 | F116: Sumit | G116: 403 | H116: CDOT S-403 | J116: 10 | K116: 115 | L116: =J116*K116 -> 1150 | M116: =tbl_Manifiestos[[#This Row],[Total Pagado]]*tbl_Manifiestos[[#This Row],[Porcentaje]] -> 1069.5 | N116: 0.93
A117: MLB | B117: =tbl_Manifiestos[[#This Row],[Factura]] & "|" & tbl_Manifiestos[[#This Row],[Proyecto OK]] & "|" & TEXT(tbl_Manifiestos[[#This Row],[Servicio]],"0.00") & "|" & TEXT(tbl_Manifiestos[[#This Row],[Costo Unitario]],"0.00") -> 2833|CDOT S-403|8.00|115.00 | C117: 2833 | D117: 45952 | E117: 82 | F117: Sumit | G117: 403 | H117: CDOT S-403 | J117: 8 | K117: 115 | L117: =J117*K117 -> 920 | M117: =tbl_Manifiestos[[#This Row],[Total Pagado]]*tbl_Manifiestos[[#This Row],[Porcentaje]] -> 855.6 | N117: 0.93
A118: MLB | B118: =tbl_Manifiestos[[#This Row],[Factura]] & "|" & tbl_Manifiestos[[#This Row],[Proyecto OK]] & "|" & TEXT(tbl_Manifiestos[[#This Row],[Servicio]],"0.00") & "|" & TEXT(tbl_Manifiestos[[#This Row],[Costo Unitario]],"0.00") -> 2833|CDOT S-403|8.00|115.00 | C118: 2833 | D118: 45953 | E118: 82 | F118: Sumit | G118: 403 | H118: CDOT S-403 | J118: 8 | K118: 115 | L118: =J118*K118 -> 920 | M118: =tbl_Manifiestos[[#This Row],[Total Pagado]]*tbl_Manifiestos[[#This Row],[Porcentaje]] -> 855.6 | N118: 0.93
A119: MLB | B119: =tbl_Manifiestos[[#This Row],[Factura]] & "|" & tbl_Manifiestos[[#This Row],[Proyecto OK]] & "|" & TEXT(tbl_Manifiestos[[#This Row],[Servicio]],"0.00") & "|" & TEXT(tbl_Manifiestos[[#This Row],[Costo Unitario]],"0.00") -> 2833|CDOT S-403|9.00|115.00 | C119: 2833 | D119: 45954 | E119: 82 | F119: Sumit | G119: 403 | H119: CDOT S-403 | J119: 9 | K119: 115 | L119: =J119*K119 -> 1035 | M119: =tbl_Manifiestos[[#This Row],[Total Pagado]]*tbl_Manifiestos[[#This Row],[Porcentaje]] -> 962.55 | N119: 0.93
A120: MLB | B120: =tbl_Manifiestos[[#This Row],[Factura]] & "|" & tbl_Manifiestos[[#This Row],[Proyecto OK]] & "|" & TEXT(tbl_Manifiestos[[#This Row],[Servicio]],"0.00") & "|" & TEXT(tbl_Manifiestos[[#This Row],[Costo Unitario]],"0.00") -> 2850|CDOT S-403|8.00|115.00 | C120: 2850 | D120: 45957 | E120: 82 | F120: Sumit | G120: 403 | H120: CDOT S-403 | J120: 8 | K120: 115 | L120: =J120*K120 -> 920 | M120: =tbl_Manifiestos[[#This Row],[Total Pagado]]*tbl_Manifiestos[[#This Row],[Porcentaje]] -> 855.6 | N120: 0.93
A121: MLB | B121: =tbl_Manifiestos[[#This Row],[Factura]] & "|" & tbl_Manifiestos[[#This Row],[Proyecto OK]] & "|" & TEXT(tbl_Manifiestos[[#This Row],[Servicio]],"0.00") & "|" & TEXT(tbl_Manifiestos[[#This Row],[Costo Unitario]],"0.00") -> 2850|CDOT S-403|8.00|115.00 | C121: 2850 | D121: 45958 | E121: 82 | F121: Sumit | G121: 403 | H121: CDOT S-403 | J121: 8 | K121: 115 | L121: =J121*K121 -> 920 | M121: =tbl_Manifiestos[[#This Row],[Total Pagado]]*tbl_Manifiestos[[#This Row],[Porcentaje]] -> 855.6 | N121: 0.93
... A167: AAA | B167: =tbl_Manifiestos[[#This Row],[Factura]] & "|" & tbl_Manifiestos[[#This Row],[Proyecto OK]] & "|" & TEXT(tbl_Manifiestos[[#This Row],[Servicio]],"0.00") & "|" & TEXT(tbl_Manifiestos[[#This Row],[Costo Unitario]],"0.00") -> 2925|CDOT S-403|4.00|115.00 | C167: 2925 | D167: 45985 | E167: 308 | F167: Sumit | G167: 403 | H167: CDOT S-403 | J167: 4 | K167: 115 | L167: =J167*K167 -> 460 | M167: =tbl_Manifiestos[[#This Row],[Total Pagado]]*tbl_Manifiestos[[#This Row],[Porcentaje]] -> 427.8 | N167: 0.93
A168: UMBRELLA | B168: =tbl_Manifiestos[[#This Row],[Factura]] & "|" & tbl_Manifiestos[[#This Row],[Proyecto OK]] & "|" & TEXT(tbl_Manifiestos[[#This Row],[Servicio]],"0.00") & "|" & TEXT(tbl_Manifiestos[[#This Row],[Costo Unitario]],"0.00") -> 2309|CDOT S-603|8.00|105.00 | C168: 2309 | D168: 45621 | E168: 28 | F168: Sumit | G168: 603 | H168: CDOT S-603 | J168: 8 | K168: 105 | L168: 840 | M168: =tbl_Manifiestos[[#This Row],[Total Pagado]]*tbl_Manifiestos[[#This Row],[Porcentaje]] -> 756 | N168: 0.9
A169: UMBRELLA | B169: =tbl_Manifiestos[[#This Row],[Factura]] & "|" & tbl_Manifiestos[[#This Row],[Proyecto OK]] & "|" & TEXT(tbl_Manifiestos[[#This Row],[Servicio]],"0.00") & "|" & TEXT(tbl_Manifiestos[[#This Row],[Costo Unitario]],"0.00") -> 2642|CDOT S-603|9.00|105.00 | C169: 2642 | D169: 45869 | E169: 28 | F169: Sumit | G169: 603 | H169: CDOT S-603 | J169: 9 | K169: 105 | L169: 945 | M169: =tbl_Manifiestos[[#This Row],[Total Pagado]]*tbl_Manifiestos[[#This Row],[Porcentaje]] -> 850.5 | N169: 0.9
A170: UMBRELLA | B170: =tbl_Manifiestos[[#This Row],[Factura]] & "|" & tbl_Manifiestos[[#This Row],[Proyecto OK]] & "|" & TEXT(tbl_Manifiestos[[#This Row],[Servicio]],"0.00") & "|" & TEXT(tbl_Manifiestos[[#This Row],[Costo Unitario]],"0.00") -> 2642|CDOT S-603|9.25|105.00 | C170: 2642 | D170: 45870 | E170: 28 | F170: Sumit | G170: 603 | H170: CDOT S-603 | J170: 9.25 | K170: 105 | L170: 971.25 | M170: =tbl_Manifiestos[[#This Row],[Total Pagado]]*tbl_Manifiestos[[#This Row],[Porcentaje]] -> 874.125 | N170: 0.9
A171: BR | B171: =tbl_Manifiestos[[#This Row],[Factura]] & "|" & tbl_Manifiestos[[#This Row],[Proyecto OK]] & "|" & TEXT(tbl_Manifiestos[[#This Row],[Servicio]],"0.00") & "|" & TEXT(tbl_Manifiestos[[#This Row],[Costo Unitario]],"0.00") -> 2642|CDOT S-603|7.00|105.00 | C171: 2642 | D171: 45868 | E171: 371 | F171: Sumit | G171: 603 | H171: CDOT S-603 | J171: 7 | K171: 105 | L171: 735 | M171: =tbl_Manifiestos[[#This Row],[Total Pagado]]*tbl_Manifiestos[[#This Row],[Porcentaje]] -> 661.5 | N171: 0.9
A172: J&O | B172: =tbl_Manifiestos[[#This Row],[Factura]] & "|" & tbl_Manifiestos[[#This Row],[Proyecto OK]] & "|" & TEXT(tbl_Manifiestos[[#This Row],[Servicio]],"0.00") & "|" & TEXT(tbl_Manifiestos[[#This Row],[Costo Unitario]],"0.00") -> 2642|CDOT S-603|9.00|105.00 | C172: 2642 | D172: 45866 | E172: 676 | F172: Sumit | G172: 603 | H172: CDOT S-603 | J172: 9 | K172: 105 | L172: 945 | M172: =tbl_Manifiestos[[#This Row],[Total Pagado]]*tbl_Manifiestos[[#This Row],[Porcentaje]] -> 850.5 | N172: 0.9
A173: J&O | B173: =tbl_Manifiestos[[#This Row],[Factura]] & "|" & tbl_Manifiestos[[#This Row],[Proyecto OK]] & "|" & TEXT(tbl_Manifiestos[[#This Row],[Servicio]],"0.00") & "|" & TEXT(tbl_Manifiestos[[#This Row],[Costo Unitario]],"0.00") -> 2642|CDOT S-603|9.00|105.00 | C173: 2642 | D173: 45867 | E173: 676 | F173: Sumit | G173: 603 | H173: CDOT S-603 | J173: 9 | K173: 105 | L173: 945 | M173: =tbl_Manifiestos[[#This Row],[Total Pagado]]*tbl_Manifiestos[[#This Row],[Porcentaje]] -> 850.5 | N173: 0.9
A174: J&O | B174: =tbl_Manifiestos[[#This Row],[Factura]] & "|" & tbl_Manifiestos[[#This Row],[Proyecto OK]] & "|" & TEXT(tbl_Manifiestos[[#This Row],[Servicio]],"0.00") & "|" & TEXT(tbl_Manifiestos[[#This Row],[Costo Unitario]],"0.00") -> 2642|CDOT S-603|9.00|105.00 | C174: 2642 | D174: 45868 | E174: 683 | F174: Sumit | G174: 603 | H174: CDOT S-603 | J174: 9 | K174: 105 | L174: 945 | M174: =tbl_Manifiestos[[#This Row],[Total Pagado]]*tbl_Manifiestos[[#This Row],[Porcentaje]] -> 850.5 | N174: 0.9
A175: Alysa | B175: =tbl_Manifiestos[[#This Row],[Factura]] & "|" & tbl_Manifiestos[[#This Row],[Proyecto OK]] & "|" & TEXT(tbl_Manifiestos[[#This Row],[Servicio]],"0.00") & "|" & TEXT(tbl_Manifiestos[[#This Row],[Costo Unitario]],"0.00") -> 2657|CDOT S-603|9.00|105.00 | C175: 2657 | D175: 45874 | E175: 701 | F175: Sumit | G175: 603 | H175: CDOT S-603 | J175: 9 | K175: 105 | L175: 945 | M175: =tbl_Manifiestos[[#This Row],[Total Pagado]]*tbl_Manifiestos[[#This Row],[Porcentaje]] -> 850.5 | N175: 0.9
A176: J&O | B176: =tbl_Manifiestos[[#This Row],[Factura]] & "|" & tbl_Manifiestos[[#This Row],[Proyecto OK]] & "|" & TEXT(tbl_Manifiestos[[#This Row],[Servicio]],"0.00") & "|" & TEXT(tbl_Manifiestos[[#This Row],[Costo Unitario]],"0.00") -> 2670|CDOT S-603|7.50|105.00 | C176: 2670 | D176: 45883 | E176: 676 | F176: Sumit | G176: 603 | H176: CDOT S-603 | J176: 7.5 | K176: 105 | L176: 787.5 | M176: =tbl_Manifiestos[[#This Row],[Total Pagado]]*tbl_Manifiestos[[#This Row],[Porcentaje]] -> 708.75 | N176: 0.9
A177: UMBRELLA | B177: =tbl_Manifiestos[[#This Row],[Factura]] & "|" & tbl_Manifiestos[[#This Row],[Proyecto OK]] & "|" & TEXT(tbl_Manifiestos[[#This Row],[Servicio]],"0.00") & "|" & TEXT(tbl_Manifiestos[[#This Row],[Costo Unitario]],"0.00") -> 2670|CDOT S-603|8.50|105.00 | C177: 2670 | D177: 45883 | E177: 661 | F177: Sumit | G177: 603 | H177: CDOT S-603 | J177: 8.5 | K177: 105 | L177: 892.5 | M177: =tbl_Manifiestos[[#This Row],[Total Pagado]]*tbl_Manifiestos[[#This Row],[Porcentaje]] -> 803.25 | N177: 0.9
A178: HERRERA | B178: =tbl_Manifiestos[[#This Row],[Factura]] & "|" & tbl_Manifiestos[[#This Row],[Proyecto OK]] & "|" & TEXT(tbl_Manifiestos[[#This Row],[Servicio]],"0.00") & "|" & TEXT(tbl_Manifiestos[[#This Row],[Costo Unitario]],"0.00") -> 2683|CDOT S-603|7.75|105.00 | C178: 2683 | D178: 45887 | E178: 92 | F178: Sumit | G178: 603 | H178: CDOT S-603 | J178: 7.75 | K178: 105 | L178: 813.75 | M178: =tbl_Manifiestos[[#This Row],[Total Pagado]]*tbl_Manifiestos[[#This Row],[Porcentaje]] -> 732.375 | N178: 0.9
A179: UMBRELLA | B179: =tbl_Manifiestos[[#This Row],[Factura]] & "|" & tbl_Manifiestos[[#This Row],[Proyecto OK]] & "|" & TEXT(tbl_Manifiestos[[#This Row],[Servicio]],"0.00") & "|" & TEXT(tbl_Manifiestos[[#This Row],[Costo Unitario]],"0.00") -> 2683|CDOT S-603|8.25|105.00 | C179: 2683 | D179: 45891 | E179: 76 | F179: Sumit | G179: 603 | H179: CDOT S-603 | J179: 8.25 | K179: 105 | L179: 866.25 | M179: =tbl_Manifiestos[[#This Row],[Total Pagado]]*tbl_Manifiestos[[#This Row],[Porcentaje]] -> 779.625 | N179: 0.9
... A191: WO | B191: =tbl_Manifiestos[[#This Row],[Factura]] & "|" & tbl_Manifiestos[[#This Row],[Proyecto OK]] & "|" & TEXT(tbl_Manifiestos[[#This Row],[Servicio]],"0.00") & "|" & TEXT(tbl_Manifiestos[[#This Row],[Costo Unitario]],"0.00") -> 2870|CDOT S-603|8.00|105.00 | C191: 2870 | D191: 45968 | E191: 201 | F191: Sumit | G191: 603 | H191: CDOT S-603 | J191: 8 | K191: 105 | L191: 840 | M191: =tbl_Manifiestos[[#This Row],[Total Pagado]]*tbl_Manifiestos[[#This Row],[Porcentaje]] -> 756 | N191: 0.9
A192: LT | B192: =tbl_Manifiestos[[#This Row],[Factura]] & "|" & tbl_Manifiestos[[#This Row],[Proyecto OK]] & "|" & TEXT(tbl_Manifiestos[[#This Row],[Servicio]],"0.00") & "|" & TEXT(tbl_Manifiestos[[#This Row],[Costo Unitario]],"0.00") -> 2309|CDOT S-603|8.75|110.00 | C192: 2309 | D192: 45638 | E192: 325 | F192: Sumit | G192: 603 | H192: CDOT S-603 | J192: 8.75 | K192: 110 | L192: =J192*K192 -> 962.5 | M192: =tbl_Manifiestos[[#This Row],[Total Pagado]]*tbl_Manifiestos[[#This Row],[Porcentaje]] -> 895.125 | N192: 0.93
A193: LT | B193: =tbl_Manifiestos[[#This Row],[Factura]] & "|" & tbl_Manifiestos[[#This Row],[Proyecto OK]] & "|" & TEXT(tbl_Manifiestos[[#This Row],[Servicio]],"0.00") & "|" & TEXT(tbl_Manifiestos[[#This Row],[Costo Unitario]],"0.00") -> 2309|CDOT S-603|9.25|110.00 | C193: 2309 | D193: 45637 | E193: 325 | F193: Sumit | G193: 603 | H193: CDOT S-603 | J193: 9.25 | K193: 110 | L193: =J193*K193 -> 1017.5 | M193: =tbl_Manifiestos[[#This Row],[Total Pagado]]*tbl_Manifiestos[[#This Row],[Porcentaje]] -> 946.275 | N193: 0.93
A194: LT | B194: =tbl_Manifiestos[[#This Row],[Factura]] & "|" & tbl_Manifiestos[[#This Row],[Proyecto OK]] & "|" & TEXT(tbl_Manifiestos[[#This Row],[Servicio]],"0.00") & "|" & TEXT(tbl_Manifiestos[[#This Row],[Costo Unitario]],"0.00") -> 2309|CDOT S-603|9.25|110.00 | C194: 2309 | D194: 45639 | E194: 325 | F194: Sumit | G194: 603 | H194: CDOT S-603 | J194: 9.25 | K194: 110 | L194: =J194*K194 -> 1017.5 | M194: =tbl_Manifiestos[[#This Row],[Total Pagado]]*tbl_Manifiestos[[#This Row],[Porcentaje]] -> 946.275 | N194: 0.93
A195: LT | B195: =tbl_Manifiestos[[#This Row],[Factura]] & "|" & tbl_Manifiestos[[#This Row],[Proyecto OK]] & "|" & TEXT(tbl_Manifiestos[[#This Row],[Servicio]],"0.00") & "|" & TEXT(tbl_Manifiestos[[#This Row],[Costo Unitario]],"0.00") -> 2309|CDOT S-603|10.00|110.00 | C195: 2309 | D195: 45635 | E195: 325 | F195: Sumit | G195: 603 | H195: CDOT S-603 | J195: 10 | K195: 110 | L195: =J195*K195 -> 1100 | M195: =tbl_Manifiestos[[#This Row],[Total Pagado]]*tbl_Manifiestos[[#This Row],[Porcentaje]] -> 1023 | N195: 0.93
A196: LT | B196: =tbl_Manifiestos[[#This Row],[Factura]] & "|" & tbl_Manifiestos[[#This Row],[Proyecto OK]] & "|" & TEXT(tbl_Manifiestos[[#This Row],[Servicio]],"0.00") & "|" & TEXT(tbl_Manifiestos[[#This Row],[Costo Unitario]],"0.00") -> 2309|CDOT S-603|8.00|110.00 | C196: 2309 | D196: 45642 | E196: 325 | F196: Sumit | G196: 603 | H196: CDOT S-603 | J196: 8 | K196: 110 | L196: =J196*K196 -> 880 | M196: =tbl_Manifiestos[[#This Row],[Total Pagado]]*tbl_Manifiestos[[#This Row],[Porcentaje]] -> 818.4 | N196: 0.93
A197: LT | B197: =tbl_Manifiestos[[#This Row],[Factura]] & "|" & tbl_Manifiestos[[#This Row],[Proyecto OK]] & "|" & TEXT(tbl_Manifiestos[[#This Row],[Servicio]],"0.00") & "|" & TEXT(tbl_Manifiestos[[#This Row],[Costo Unitario]],"0.00") -> 2309|CDOT S-603|8.00|110.00 | C197: 2309 | D197: 45636 | E197: 325 | F197: Sumit | G197: 603 | H197: CDOT S-603 | J197: 8 | K197: 110 | L197: =J197*K197 -> 880 | M197: =tbl_Manifiestos[[#This Row],[Total Pagado]]*tbl_Manifiestos[[#This Row],[Porcentaje]] -> 818.4 | N197: 0.93
A198: LT | B198: =tbl_Manifiestos[[#This Row],[Factura]] & "|" & tbl_Manifiestos[[#This Row],[Proyecto OK]] & "|" & TEXT(tbl_Manifiestos[[#This Row],[Servicio]],"0.00") & "|" & TEXT(tbl_Manifiestos[[#This Row],[Costo Unitario]],"0.00") -> 2642|CDOT S-603|10.50|115.00 | C198: 2642 | D198: 45866 | E198: 325 | F198: Sumit | G198: 603 | H198: CDOT S-603 | J198: 10.5 | K198: 115 | L198: =J198*K198 -> 1207.5 | M198: =tbl_Manifiestos[[#This Row],[Total Pagado]]*tbl_Manifiestos[[#This Row],[Porcentaje]] -> 1122.975 | N198: 0.93
A199: LT | B199: =tbl_Manifiestos[[#This Row],[Factura]] & "|" & tbl_Manifiestos[[#This Row],[Proyecto OK]] & "|" & TEXT(tbl_Manifiestos[[#This Row],[Servicio]],"0.00") & "|" & TEXT(tbl_Manifiestos[[#This Row],[Costo Unitario]],"0.00") -> 2642|CDOT S-603|9.50|115.00 | C199: 2642 | D199: 45866 | E199: 114 | F199: Sumit | G199: 603 | H199: CDOT S-603 | J199: 9.5 | K199: 115 | L199: =J199*K199 -> 1092.5 | M199: =tbl_Manifiestos[[#This Row],[Total Pagado]]*tbl_Manifiestos[[#This Row],[Porcentaje]] -> 1016.025 | N199: 0.93
A200: LT | B200: =tbl_Manifiestos[[#This Row],[Factura]] & "|" & tbl_Manifiestos[[#This Row],[Proyecto OK]] & "|" & TEXT(tbl_Manifiestos[[#This Row],[Servicio]],"0.00") & "|" & TEXT(tbl_Manifiestos[[#This Row],[Costo Unitario]],"0.00") -> 2642|CDOT S-603|7.75|115.00 | C200: 2642 | D200: 45866 | E200: 67 | F200: Sumit | G200: 603 | H200: CDOT S-603 | J200: 7.75 | K200: 115 | L200: =J200*K200 -> 891.25 | M200: =tbl_Manifiestos[[#This Row],[Total Pagado]]*tbl_Manifiestos[[#This Row],[Porcentaje]] -> 828.8625 | N200: 0.93
A201: LT | B201: =tbl_Manifiestos[[#This Row],[Factura]] & "|" & tbl_Manifiestos[[#This Row],[Proyecto OK]] & "|" & TEXT(tbl_Manifiestos[[#This Row],[Servicio]],"0.00") & "|" & TEXT(tbl_Manifiestos[[#This Row],[Costo Unitario]],"0.00") -> 2642|CDOT S-603|10.00|115.00 | C201: 2642 | D201: 45867 | E201: 325 | F201: Sumit | G201: 603 | H201: CDOT S-603 | J201: 10 | K201: 115 | L201: =J201*K201 -> 1150 | M201: =tbl_Manifiestos[[#This Row],[Total Pagado]]*tbl_Manifiestos[[#This Row],[Porcentaje]] -> 1069.5 | N201: 0.93
A202: LT | B202: =tbl_Manifiestos[[#This Row],[Factura]] & "|" & tbl_Manifiestos[[#This Row],[Proyecto OK]] & "|" & TEXT(tbl_Manifiestos[[#This Row],[Servicio]],"0.00") & "|" & TEXT(tbl_Manifiestos[[#This Row],[Costo Unitario]],"0.00") -> 2642|CDOT S-603|9.00|115.00 | C202: 2642 | D202: 45867 | E202: 114 | F202: Sumit | G202: 603 | H202: CDOT S-603 | J202: 9 | K202: 115 | L202: =J202*K202 -> 1035 | M202: =tbl_Manifiestos[[#This Row],[Total Pagado]]*tbl_Manifiestos[[#This Row],[Porcentaje]] -> 962.55 | N202: 0.93
A203: LT | B203: =tbl_Manifiestos[[#This Row],[Factura]] & "|" & tbl_Manifiestos[[#This Row],[Proyecto OK]] & "|" & TEXT(tbl_Manifiestos[[#This Row],[Servicio]],"0.00") & "|" & TEXT(tbl_Manifiestos[[#This Row],[Costo Unitario]],"0.00") -> 2642|CDOT S-603|8.50|115.00 | C203: 2642 | D203: 45868 | E203: 114 | F203: Sumit | G203: 603 | H203: CDOT S-603 | J203: 8.5 | K203: 115 | L203: =J203*K203 -> 977.5 | M203: =tbl_Manifiestos[[#This Row],[Total Pagado]]*tbl_Manifiestos[[#This Row],[Porcentaje]] -> 909.075 | N203: 0.93
A204: LT | B204: =tbl_Manifiestos[[#This Row],[Factura]] & "|" & tbl_Manifiestos[[#This Row],[Proyecto OK]] & "|" & TEXT(tbl_Manifiestos[[#This Row],[Servicio]],"0.00") & "|" & TEXT(tbl_Manifiestos[[#This Row],[Costo Unitario]],"0.00") -> 2642|CDOT S-603|9.50|115.00 | C204: 2642 | D204: 45869 | E204: 114 | F204: Sumit | G204: 603 | H204: CDOT S-603 | J204: 9.5 | K204: 115 | L204: =J204*K204 -> 1092.5 | M204: =tbl_Manifiestos[[#This Row],[Total Pagado]]*tbl_Manifiestos[[#This Row],[Porcentaje]] -> 1016.025 | N204: 0.93
A205: LT | B205: =tbl_Manifiestos[[#This Row],[Factura]] & "|" & tbl_Manifiestos[[#This Row],[Proyecto OK]] & "|" & TEXT(tbl_Manifiestos[[#This Row],[Servicio]],"0.00") & "|" & TEXT(tbl_Manifiestos[[#This Row],[Costo Unitario]],"0.00") -> 2642|CDOT S-603|9.00|115.00 | C205: 2642 | D205: 45870 | E205: 114 | F205: Sumit | G205: 603 | H205: CDOT S-603 | J205: 9 | K205: 115 | L205: =J205*K205 -> 1035 | M205: =tbl_Manifiestos[[#This Row],[Total Pagado]]*tbl_Manifiestos[[#This Row],[Porcentaje]] -> 962.55 | N205: 0.93
A206: LT | B206: =tbl_Manifiestos[[#This Row],[Factura]] & "|" & tbl_Manifiestos[[#This Row],[Proyecto OK]] & "|" & TEXT(tbl_Manifiestos[[#This Row],[Servicio]],"0.00") & "|" & TEXT(tbl_Manifiestos[[#This Row],[Costo Unitario]],"0.00") -> 2657|CDOT S-603|9.50|115.00 | C206: 2657 | D206: 45873 | E206: 356 | F206: Sumit | G206: 603 | H206: CDOT S-603 | J206: 9.5 | K206: 115 | L206: =J206*K206 -> 1092.5 | M206: =tbl_Manifiestos[[#This Row],[Total Pagado]]*tbl_Manifiestos[[#This Row],[Porcentaje]] -> 1016.025 | N206: 0.93
A207: LT | B207: =tbl_Manifiestos[[#This Row],[Factura]] & "|" & tbl_Manifiestos[[#This Row],[Proyecto OK]] & "|" & TEXT(tbl_Manifiestos[[#This Row],[Servicio]],"0.00") & "|" & TEXT(tbl_Manifiestos[[#This Row],[Costo Unitario]],"0.00") -> 2657|CDOT S-603|8.75|115.00 | C207: 2657 | D207: 45876 | E207: 356 | F207: Sumit | G207: 603 | H207: CDOT S-603 | J207: 8.75 | K207: 115 | L207: =J207*K207 -> 1006.25 | M207: =tbl_Manifiestos[[#This Row],[Total Pagado]]*tbl_Manifiestos[[#This Row],[Porcentaje]] -> 935.8125 | N207: 0.93
A208: LT | B208: =tbl_Manifiestos[[#This Row],[Factura]] & "|" & tbl_Manifiestos[[#This Row],[Proyecto OK]] & "|" & TEXT(tbl_Manifiestos[[#This Row],[Servicio]],"0.00") & "|" & TEXT(tbl_Manifiestos[[#This Row],[Costo Unitario]],"0.00") -> 2670|CDOT S-603|8.50|115.00 | C208: 2670 | D208: 45880 | E208: 114 | F208: Sumit | G208: 603 | H208: CDOT S-603 | J208: 8.5 | K208: 115 | L208: =J208*K208 -> 977.5 | M208: =tbl_Manifiestos[[#This Row],[Total Pagado]]*tbl_Manifiestos[[#This Row],[Porcentaje]] -> 909.075 | N208: 0.93
A209: LT | B209: =tbl_Manifiestos[[#This Row],[Factura]] & "|" & tbl_Manifiestos[[#This Row],[Proyecto OK]] & "|" & TEXT(tbl_Manifiestos[[#This Row],[Servicio]],"0.00") & "|" & TEXT(tbl_Manifiestos[[#This Row],[Costo Unitario]],"0.00") -> 2670|CDOT S-603|10.25|115.00 | C209: 2670 | D209: 45881 | E209: 114 | F209: Sumit | G209: 603 | H209: CDOT S-603 | J209: 10.25 | K209: 115 | L209: =J209*K209 -> 1178.75 | M209: =tbl_Manifiestos[[#This Row],[Total Pagado]]*tbl_Manifiestos[[#This Row],[Porcentaje]] -> 1096.2375 | N209: 0.93
... A314: MLB | B314: =tbl_Manifiestos[[#This Row],[Factura]] & "|" & tbl_Manifiestos[[#This Row],[Proyecto OK]] & "|" & TEXT(tbl_Manifiestos[[#This Row],[Servicio]],"0.00") & "|" & TEXT(tbl_Manifiestos[[#This Row],[Costo Unitario]],"0.00") -> 2763|CDOT S-603|8.50|115.00 | C314: 2763 | D314: 45923 | E314: 11 | F314: Sumit | G314: 603 | H314: CDOT S-603 | J314: 8.5 | K314: 115 | L314: =J314*K314 -> 977.5 | M314: =tbl_Manifiestos[[#This Row],[Total Pagado]]*tbl_Manifiestos[[#This Row],[Porcentaje]] -> 909.075 | N314: 0.93
A315: MLB | B315: =tbl_Manifiestos[[#This Row],[Factura]] & "|" & tbl_Manifiestos[[#This Row],[Proyecto OK]] & "|" & TEXT(tbl_Manifiestos[[#This Row],[Servicio]],"0.00") & "|" & TEXT(tbl_Manifiestos[[#This Row],[Costo Unitario]],"0.00") -> 2763|CDOT S-603|1.00|250.00 | C315: 2763 | D315: 45922 | E315: 11 | F315: Sumit | G315: 603 | H315: CDOT S-603 | J315: 1 | K315: 250 | M315: =tbl_Manifiestos[[#This Row],[Total Pagado]]*tbl_Manifiestos[[#This Row],[Porcentaje]] -> 0 | N315: 0.93
A316: MLB | B316: =tbl_Manifiestos[[#This Row],[Factura]] & "|" & tbl_Manifiestos[[#This Row],[Proyecto OK]] & "|" & TEXT(tbl_Manifiestos[[#This Row],[Servicio]],"0.00") & "|" & TEXT(tbl_Manifiestos[[#This Row],[Costo Unitario]],"0.00") -> 2782|CDOT S-603|8.50|115.00 | C316: 2782 | D316: 45932 | E316: 58 | F316: Sumit | G316: 603 | H316: CDOT S-603 | J316: 8.5 | K316: 115 | L316: =J316*K316 -> 977.5 | M316: =tbl_Manifiestos[[#This Row],[Total Pagado]]*tbl_Manifiestos[[#This Row],[Porcentaje]] -> 909.075 | N316: 0.93
A317: MLB | B317: =tbl_Manifiestos[[#This Row],[Factura]] & "|" & tbl_Manifiestos[[#This Row],[Proyecto OK]] & "|" & TEXT(tbl_Manifiestos[[#This Row],[Servicio]],"0.00") & "|" & TEXT(tbl_Manifiestos[[#This Row],[Costo Unitario]],"0.00") -> 2797|CDOT S-603|10.50|115.00 | C317: 2797 | D317: 45936 | E317: 58 | F317: Sumit | G317: 603 | H317: CDOT S-603 | J317: 10.5 | K317: 115 | L317: 1207.5 | M317: =tbl_Manifiestos[[#This Row],[Total Pagado]]*tbl_Manifiestos[[#This Row],[Porcentaje]] -> 1122.975 | N317: 0.93
A318: MLB | B318: =tbl_Manifiestos[[#This Row],[Factura]] & "|" & tbl_Manifiestos[[#This Row],[Proyecto OK]] & "|" & TEXT(tbl_Manifiestos[[#This Row],[Servicio]],"0.00") & "|" & TEXT(tbl_Manifiestos[[#This Row],[Costo Unitario]],"0.00") -> 2797|CDOT S-603|8.50|115.00 | C318: 2797 | D318: 45938 | E318: 58 | F318: Sumit | G318: 603 | H318: CDOT S-603 | J318: 8.5 | K318: 115 | L318: 977.5 | M318: =tbl_Manifiestos[[#This Row],[Total Pagado]]*tbl_Manifiestos[[#This Row],[Porcentaje]] -> 909.075 | N318: 0.93
A319: MLB | B319: =tbl_Manifiestos[[#This Row],[Factura]] & "|" & tbl_Manifiestos[[#This Row],[Proyecto OK]] & "|" & TEXT(tbl_Manifiestos[[#This Row],[Servicio]],"0.00") & "|" & TEXT(tbl_Manifiestos[[#This Row],[Costo Unitario]],"0.00") -> 2797|CDOT S-603|9.00|115.00 | C319: 2797 | D319: 45939 | E319: 58 | F319: Sumit | G319: 603 | H319: CDOT S-603 | J319: 9 | K319: 115 | L319: 1035 | M319: =tbl_Manifiestos[[#This Row],[Total Pagado]]*tbl_Manifiestos[[#This Row],[Porcentaje]] -> 962.55 | N319: 0.93
A320: MLB | B320: =tbl_Manifiestos[[#This Row],[Factura]] & "|" & tbl_Manifiestos[[#This Row],[Proyecto OK]] & "|" & TEXT(tbl_Manifiestos[[#This Row],[Servicio]],"0.00") & "|" & TEXT(tbl_Manifiestos[[#This Row],[Costo Unitario]],"0.00") -> 2812|CDOT S-603|9.50|115.00 | C320: 2812 | D320: 45943 | E320: 58 | F320: Sumit | G320: 603 | H320: CDOT S-603 | J320: 9.5 | K320: 115 | L320: =J320*K320 -> 1092.5 | M320: =tbl_Manifiestos[[#This Row],[Total Pagado]]*tbl_Manifiestos[[#This Row],[Porcentaje]] -> 1016.025 | N320: 0.93
A321: MLB | B321: =tbl_Manifiestos[[#This Row],[Factura]] & "|" & tbl_Manifiestos[[#This Row],[Proyecto OK]] & "|" & TEXT(tbl_Manifiestos[[#This Row],[Servicio]],"0.00") & "|" & TEXT(tbl_Manifiestos[[#This Row],[Costo Unitario]],"0.00") -> 2812|CDOT S-603|8.50|115.00 | C321: 2812 | D321: 45944 | E321: 58 | F321: Sumit | G321: 603 | H321: CDOT S-603 | J321: 8.5 | K321: 115 | L321: =J321*K321 -> 977.5 | M321: =tbl_Manifiestos[[#This Row],[Total Pagado]]*tbl_Manifiestos[[#This Row],[Porcentaje]] -> 909.075 | N321: 0.93
A322: MLB | B322: =tbl_Manifiestos[[#This Row],[Factura]] & "|" & tbl_Manifiestos[[#This Row],[Proyecto OK]] & "|" & TEXT(tbl_Manifiestos[[#This Row],[Servicio]],"0.00") & "|" & TEXT(tbl_Manifiestos[[#This Row],[Costo Unitario]],"0.00") -> 2812|CDOT S-603|6.50|115.00 | C322: 2812 | D322: 45945 | E322: 58 | F322: Sumit | G322: 603 | H322: CDOT S-603 | J322: 6.5 | K322: 115 | L322: =J322*K322 -> 747.5 | M322: =tbl_Manifiestos[[#This Row],[Total Pagado]]*tbl_Manifiestos[[#This Row],[Porcentaje]] -> 695.175 | N322: 0.93
A323: MLB | B323: =tbl_Manifiestos[[#This Row],[Factura]] & "|" & tbl_Manifiestos[[#This Row],[Proyecto OK]] & "|" & TEXT(tbl_Manifiestos[[#This Row],[Servicio]],"0.00") & "|" & TEXT(tbl_Manifiestos[[#This Row],[Costo Unitario]],"0.00") -> 2812|CDOT S-603|9.00|115.00 | C323: 2812 | D323: 45946 | E323: 58 | F323: Sumit | G323: 603 | H323: CDOT S-603 | J323: 9 | K323: 115 | L323: =J323*K323 -> 1035 | M323: =tbl_Manifiestos[[#This Row],[Total Pagado]]*tbl_Manifiestos[[#This Row],[Porcentaje]] -> 962.55 | N323: 0.93
A324: MLB | B324: =tbl_Manifiestos[[#This Row],[Factura]] & "|" & tbl_Manifiestos[[#This Row],[Proyecto OK]] & "|" & TEXT(tbl_Manifiestos[[#This Row],[Servicio]],"0.00") & "|" & TEXT(tbl_Manifiestos[[#This Row],[Costo Unitario]],"0.00") -> 2812|CDOT S-603|9.50|115.00 | C324: 2812 | D324: 45947 | E324: 58 | F324: Sumit | G324: 603 | H324: CDOT S-603 | J324: 9.5 | K324: 115 | L324: =J324*K324 -> 1092.5 | M324: =tbl_Manifiestos[[#This Row],[Total Pagado]]*tbl_Manifiestos[[#This Row],[Porcentaje]] -> 1016.025 | N324: 0.93
A325: MLB | B325: =tbl_Manifiestos[[#This Row],[Factura]] & "|" & tbl_Manifiestos[[#This Row],[Proyecto OK]] & "|" & TEXT(tbl_Manifiestos[[#This Row],[Servicio]],"0.00") & "|" & TEXT(tbl_Manifiestos[[#This Row],[Costo Unitario]],"0.00") -> 2870|CDOT S-603|9.00|115.00 | C325: 2870 | D325: 45964 | E325: 82 | F325: Sumit | G325: 603 | H325: CDOT S-603 | J325: 9 | K325: 115 | L325: =J325*K325 -> 1035 | M325: =tbl_Manifiestos[[#This Row],[Total Pagado]]*tbl_Manifiestos[[#This Row],[Porcentaje]] -> 962.55 | N325: 0.93
A326: MLB | B326: =tbl_Manifiestos[[#This Row],[Factura]] & "|" & tbl_Manifiestos[[#This Row],[Proyecto OK]] & "|" & TEXT(tbl_Manifiestos[[#This Row],[Servicio]],"0.00") & "|" & TEXT(tbl_Manifiestos[[#This Row],[Costo Unitario]],"0.00") -> 2870|CDOT S-603|8.75|115.00 | C326: 2870 | D326: 45965 | E326: 82 | F326: Sumit | G326: 603 | H326: CDOT S-603 | J326: 8.75 | K326: 115 | L326: =J326*K326 -> 1006.25 | M326: =tbl_Manifiestos[[#This Row],[Total Pagado]]*tbl_Manifiestos[[#This Row],[Porcentaje]] -> 935.8125 | N326: 0.93
A327: MLB | B327: =tbl_Manifiestos[[#This Row],[Factura]] & "|" & tbl_Manifiestos[[#This Row],[Proyecto OK]] & "|" & TEXT(tbl_Manifiestos[[#This Row],[Servicio]],"0.00") & "|" & TEXT(tbl_Manifiestos[[#This Row],[Costo Unitario]],"0.00") -> 2870|CDOT S-603|8.00|115.00 | C327: 2870 | D327: 45968 | E327: 82 | F327: Sumit | G327: 603 | H327: CDOT S-603 | J327: 8 | K327: 115 | L327: =J327*K327 -> 920 | M327: =tbl_Manifiestos[[#This Row],[Total Pagado]]*tbl_Manifiestos[[#This Row],[Porcentaje]] -> 855.6 | N327: 0.93
A328: MLB | B328: =tbl_Manifiestos[[#This Row],[Factura]] & "|" & tbl_Manifiestos[[#This Row],[Proyecto OK]] & "|" & TEXT(tbl_Manifiestos[[#This Row],[Servicio]],"0.00") & "|" & TEXT(tbl_Manifiestos[[#This Row],[Costo Unitario]],"0.00") -> 2911|CDOT S-603|8.00|115.00 | C328: 2911 | D328: 45979 | E328: 58 | F328: Sumit | G328: 603 | H328: CDOT S-603 | J328: 8 | K328: 115 | L328: =J328*K328 -> 920 | M328: =tbl_Manifiestos[[#This Row],[Total Pagado]]*tbl_Manifiestos[[#This Row],[Porcentaje]] -> 855.6 | N328: 0.93
A329: MLB | B329: =tbl_Manifiestos[[#This Row],[Factura]] & "|" & tbl_Manifiestos[[#This Row],[Proyecto OK]] & "|" & TEXT(tbl_Manifiestos[[#This Row],[Servicio]],"0.00") & "|" & TEXT(tbl_Manifiestos[[#This Row],[Costo Unitario]],"0.00") -> 2911|CDOT S-603|10.50|115.00 | C329: 2911 | D329: 45980 | E329: 82 | F329: Sumit | G329: 603 | H329: CDOT S-603 | J329: 10.5 | K329: 115 | L329: =J329*K329 -> 1207.5 | M329: =tbl_Manifiestos[[#This Row],[Total Pagado]]*tbl_Manifiestos[[#This Row],[Porcentaje]] -> 1122.975 | N329: 0.93
A330: MLB | B330: =tbl_Manifiestos[[#This Row],[Factura]] & "|" & tbl_Manifiestos[[#This Row],[Proyecto OK]] & "|" & TEXT(tbl_Manifiestos[[#This Row],[Servicio]],"0.00") & "|" & TEXT(tbl_Manifiestos[[#This Row],[Costo Unitario]],"0.00") -> 2911|CDOT S-603|9.75|115.00 | C330: 2911 | D330: 45981 | E330: 82 | F330: Sumit | G330: 603 | H330: CDOT S-603 | J330: 9.75 | K330: 115 | L330: =J330*K330 -> 1121.25 | M330: =tbl_Manifiestos[[#This Row],[Total Pagado]]*tbl_Manifiestos[[#This Row],[Porcentaje]] -> 1042.7625 | N330: 0.93
A331: MLB | B331: =tbl_Manifiestos[[#This Row],[Factura]] & "|" & tbl_Manifiestos[[#This Row],[Proyecto OK]] & "|" & TEXT(tbl_Manifiestos[[#This Row],[Servicio]],"0.00") & "|" & TEXT(tbl_Manifiestos[[#This Row],[Costo Unitario]],"0.00") -> 2911|CDOT S-603|7.50|115.00 | C331: 2911 | D331: 45982 | E331: 82 | F331: Sumit | G331: 603 | H331: CDOT S-603 | J331: 7.5 | K331: 115 | L331: =J331*K331 -> 862.5 | M331: =tbl_Manifiestos[[#This Row],[Total Pagado]]*tbl_Manifiestos[[#This Row],[Porcentaje]] -> 802.125 | N331: 0.93
... A349: AAA | B349: =tbl_Manifiestos[[#This Row],[Factura]] & "|" & tbl_Manifiestos[[#This Row],[Proyecto OK]] & "|" & TEXT(tbl_Manifiestos[[#This Row],[Servicio]],"0.00") & "|" & TEXT(tbl_Manifiestos[[#This Row],[Costo Unitario]],"0.00") -> 2911|CDOT S-603|8.00|115.00 | C349: 2911 | D349: 45982 | E349: 308 | F349: Sumit | G349: 603 | H349: CDOT S-603 | J349: 8 | K349: 115 | L349: =J349*K349 -> 920 | M349: =tbl_Manifiestos[[#This Row],[Total Pagado]]*tbl_Manifiestos[[#This Row],[Porcentaje]] -> 855.6 | N349: 0.93
A350: UMBRELLA | B350: =tbl_Manifiestos[[#This Row],[Factura]] & "|" & tbl_Manifiestos[[#This Row],[Proyecto OK]] & "|" & TEXT(tbl_Manifiestos[[#This Row],[Servicio]],"0.00") & "|" & TEXT(tbl_Manifiestos[[#This Row],[Costo Unitario]],"0.00") -> 2320|CDOT S-403|9.25|105.00 | C350: 2320 | D350: 45644 | E350: 28 | F350: Sumit | G350: 635 | H350: CDOT S-403 | J350: 9.25 | K350: 105 | L350: 971.25 | M350: =tbl_Manifiestos[[#This Row],[Total Pagado]]*tbl_Manifiestos[[#This Row],[Porcentaje]] -> 874.125 | N350: 0.9
...

Sheet Dashboard
A2: Año | B2: (Todas)
A3: Mes | B3: 01
A5: Etiquetas de fila | B5: Total Cobrado a Cliente | C5: Pago Total a Broker
A6: Total general

Sheet Manifiestos Dashboard
A1: DASHBOARD
B19: Pago por cliente por periodo
B20: Fecha / Cliente | C20: Costo Unitario Total | D20: Total Pagado | E20: 90% Total
B21: 41 | C21: 220 | D21: 1100 | E21: 990
B22: 2025 | C22: 220 | D22: 1100 | E22: 990
B23: Qtr3 | C23: 220 | D23: 1100 | E23: 990
B24: Sep | C24: 220 | D24: 1100 | E24: 990
B25: 45925 | C25: 220 | D25: 1100 | E25: 990
B26: Viridian | C26: 220 | D26: 1100 | E26: 990
B27: 52.34 | C27: 100 | D27: 800 | E27: 720
B28: 55.75 | C28: 100 | D28: 800 | E28: 720
B29: 2025 | C29: 100 | D29: 800 | E29: 720
B30: Qtr2 | C30: 100 | D30: 800 | E30: 720
B31: May | C31: 100 | D31: 800 | E31: 720
B32: 45778 | C32: 100 | D32: 800 | E32: 720
B33: Foundation Mechanics | C33: 100 | D33: 800 | E33: 720
B34: 73.78 | C34: 100 | D34: 800 | E34: 720
B35: 2025 | C35: 100 | D35: 800 | E35: 720
B36: Qtr2 | C36: 100 | D36: 800 | E36: 720
B37: Apr | C37: 100 | D37: 800 | E37: 720
B38: 45770 | C38: 100 | D38: 800 | E38: 720
B39: Foundation Mechanics | C39: 100 | D39: 800 | E39: 720
B40: 82.91 | C40: 100 | D40: 800 | E40: 720
B41: 2025 | C41: 100 | D41: 800 | E41: 720
B42: Qtr2 | C42: 100 | D42: 800 | E42: 720
B43: Apr | C43: 100 | D43: 800 | E43: 720
B44: 45770 | C44: 100 | D44: 800 | E44: 720
B45: Foundation Mechanics | C45: 100 | D45: 800 | E45: 720
B46: 403 | C46: 3360 | D46: 28691.25 | E46: 25822.14
B47: 2025 | C47: 3360 | D47: 28691.25 | E47: 25822.14
B48: Qtr3 | C48: 2625 | D48: 22732.5 | E48: 20459.26
B49: Aug | C49: 1680 | D49: 14673.75 | E49: 13206.38
B50: 45870 | C50: 105 | D50: 892.5 | E50: 803.25
B51: Sumit | C51: 105 | D51: 892.5 | E51: 803.25
B52: 45873 | C52: 105 | D52: 840 | E52: 756
B53: Sumit | C53: 105 | D53: 840 | E53: 756
B54: 45874 | C54: 210 | D54: 2100 | E54: 1890
B55: Sumit | C55: 210 | D55: 2100 | E55: 1890
B56: 45875 | C56: 210 | D56: 1890 | E56: 1701
B57: Sumit | C57: 210 | D57: 1890 | E57: 1701
B58: 45876 | C58: 105 | D58: 945 | E58: 850.5
B59: Sumit | C59: 105 | D59: 945 | E59: 850.5
B60: 45881 | C60: 105 | D60: 840 | E60: 756
B61: Sumit | C61: 105 | D61: 840 | E61: 756
B62: 45882 | C62: 105 | D62: 840 | E62: 756
B63: Sumit | C63: 105 | D63: 840 | E63: 756
B64: 45884 | C64: 105 | D64: 892.5 | E64: 803.25
B65: Sumit 09703/ HERRERA | C65: 105 | D65: 892.5 | E65: 803.25
B66: 45891 | C66: 105 | D66: 945 | E66: 850.5
B67: Sumit | C67: 105 | D67: 945 | E67: 850.5
B68: 45894 | C68: 105 | D68: 787.5 | E68: 708.75
B69: Sumit | C69: 105 | D69: 787.5 | E69: 708.75
B70: 45896 | C70: 105 | D70: 945 | E70: 850.5
B71: Sumit | C71: 105 | D71: 945 | E71: 850.5
B72: 45897 | C72: 210 | D72: 1968.75 | E72: 1771.88
B73: Sumit | C73: 210 | D73: 1968.75 | E73: 1771.88
B74: 45898 | C74: 105 | D74: 787.5 | E74: 708.75
B75: Sumit | C75: 105 | D75: 787.5 | E75: 708.75
B76: Sep | C76: 945 | D76: 8058.75 | E76: 7252.88
B77: 45902 | C77: 105 | D77: 735 | E77: 661.5
B78: Sumit | C78: 105 | D78: 735 | E78: 661.5
B79: 45905 | C79: 105 | D79: 840 | E79: 756
B80: Sumit | C80: 105 | D80: 840 | E80: 756
B81: 45909 | C81: 105 | D81: 945 | E81: 850.5
B82: Sumit | C82: 105 | D82: 945 | E82: 850.5
B83: 45910 | C83: 105 | D83: 840 | E83: 756
B84: Sumit | C84: 105 | D84: 840 | E84: 756
B85: 45911 | C85: 105 | D85: 892.5 | E85: 803.25
B86: Sumit | C86: 105 | D86: 892.5 | E86: 803.25
B87: 45912 | C87: 105 | D87: 840 | E87: 756
B88: Sumit | C88: 105 | D88: 840 | E88: 756
B89: 45923 | C89: 105 | D89: 840 | E89: 756
B90: Sumit | C90: 105 | D90: 840 | E90: 756
B91: 45924 | C91: 105 | D91: 1050 | E91: 945
B92: Sumit | C92: 105 | D92: 1050 | E92: 945
B93: 45930 | C93: 105 | D93: 1076.25 | E93: 968.63
B94: Sumit | C94: 105 | D94: 1076.25 | E94: 968.63
B95: Qtr4 | C95: 735 | D95: 5958.75 | E95: 5362.88
B96: Oct | C96: 210 | D96: 1785 | E96: 1606.5
B97: 45960 | C97: 105 | D97: 945 | E97: 850.5
B98: Sumit | C98: 105 | D98: 945 | E98: 850.5
B99: 45961 | C99: 105 | D99: 840 | E99: 756
B100: Sumit | C100: 105 | D100: 840 | E100: 756
B101: Nov | C101: 525 | D101: 4173.75 | E101: 3756.38
B102: 45964 | C102: 105 | D102: 840 | E102: 756
B103: Sumit | C103: 105 | D103: 840 | E103: 756
B104: 45966 | C104: 105 | D104: 840 | E104: 756
B105: Sumit | C105: 105 | D105: 840 | E105: 756
B106: 45968 | C106: 105 | D106: 813.75 | E106: 732.38
B107: Sumit | C107: 105 | D107: 813.75 | E107: 732.38
B108: 45975 | C108: 105 | D108: 840 | E108: 756
B109: Sumit | C109: 105 | D109: 840 | E109: 756
B110: 45978 | C110: 105 | D110: 840 | E110: 756
B111: Sumit | C111: 105 | D111: 840 | E111: 756
B112: 603 | C112: 2520 | D112: 22102.5 | E112: 19892.28
B113: 2024 | C113: 105 | D113: 840 | E113: 756
B114: Qtr4 | C114: 105 | D114: 840 | E114: 756
B115: Nov | C115: 105 | D115: 840 | E115: 756
B116: 45621 | C116: 105 | D116: 840 | E116: 756
B117: Sumit | C117: 105 | D117: 840 | E117: 756
...

Sheet Totales
C3: Por Factura | D3: 2313
C4: Cobrado Total | D4: =SUMIF(tbl_Facturas[Factura],Totales!D3,tbl_Facturas[Total Cobrado]) -> 0
C5: Ofrecido a Broker | D5: =SUMIF(tbl_Manifiestos[Factura],Totales!D3,tbl_Manifiestos[Total Pagado]) -> 1000
C6: Pagado a Broker | D6: =SUMIF(tbl_Manifiestos[Factura],Totales!D3,tbl_Manifiestos[Pagado a Broker]) -> 906
C9: Por Mes
C10: Por Cliente | D10: PanOceanic
C11: Cobrado Total | D11: =SUMIF(tbl_Facturas[Factura],Totales!D10,tbl_Facturas[Total Cobrado]) -> 0
C12: Ofrecido a Broker | D12: =SUMIF(tbl_Manifiestos[Customer],Totales!D10,tbl_Manifiestos[Total Pagado]) -> 611943.25
C13: Pagado a Broker | D13: =SUMIF(tbl_Manifiestos[Customer],Totales!D10,tbl_Manifiestos[Pagado a Broker]) -> 567126.45
C15: Por Año | D15: 2025
C16: Por Mes | D16: 08
C17: Por Proyecto
C18: Cobrado Total | D18: =SUMIFS( tbl_Facturas[Total Cobrado], tbl_Facturas[Proyecto], IF(D17="", "*", D17), #REF!, IF(D16="", "*", D16), #REF!, IF(D15="", "*", D15) ) -> #REF!
C19: Ofrecido a Broker | D19: =SUMIFS( tbl_Manifiestos[Total Pagado], tbl_Manifiestos[Proyecto], IF(D17="", "*", D17), #REF!, IF(D16="", "*", D16), #REF!, IF(D15="", "*", D15) ) -> #REF!
C20: Pagado a Broker | D20: =SUMIFS( tbl_Manifiestos[Pagado a Broker], tbl_Manifiestos[Proyecto], IF(D17="", "*", D17), #REF!, IF(D16="", "*", D16), #REF!, IF(D15="", "*", D15) ) -> #REF!
